Workbook

Sheet Commission Details - 4.5.26
A1: IRON CREST SOLUTIONS — COMMISSION DETAILS
A2: Production Week Ending: 04/05/2026 | Payday: 04/10/2026
A4: SAM CHAPMAN
A5: Customer | B5: Service | C5: Tier | D5: Commission
A6: ANDREW WILLIAMS | B6: Internet | C6: 1 Gig | D6: 210
A7: DARLINE LOCKETT | B7: Internet | C7: 1 Gig | D7: 210
A8: DIANA M GUTMAN | B8: Internet | C8: 1 Gig+ | D8: 235
A9: EDWARD FLOYD | B9: Mobile | C9: Unlm. Mobile | D9: 45
A10: GLADYS LABOR | B10: Internet | C10: 1 Gig | D10: 210
A11: GLADYS LABOR | B11: TV | C11: TV | D11: 50
A12: IRVIN SWEET | B12: Internet | C12: 1 Gig | D12: 210
A13: IRVIN SWEET | B13: TV | C13: TV | D13: 50
A14: JANE M CHARLES | B14: Internet | C14: 1 Gig+ | D14: 235
A15: JEROME HANEY | B15: Internet | C15: 1 Gig | D15: 210
A16: JOANN PALESTRINI | B16: Internet | C16: 1 Gig | D16: 210
A17: RAPHAEL MARSH | B17: Internet | C17: 1 Gig | D17: 210
... A20: THERESA KUGELMAN | B20: Internet | C20: 1 Gig | D20: 210
A21: 15 Orders | D21: =SUM(D6:D20) -> 2555
A23: PAYOUT SUMMARY
A24: Gross Commission | B24: 2555
A25: Reserve (15%) | B25: -383.25
A26: YTD Reserve Balance | B26: 1473.5
A27: Net Comp (after reserve) | B27: 2171.75
A28: DD Fee | B28: -2.5
A29: PAYROLL | B29: 2169.25
A32: JOSE LUIS MOLINA
A33: Customer | B33: Service | C33: Tier | D33: Commission
A34: CRISTAL MARMOL | B34: Internet | C34: 1 Gig+ | D34: 235
A35: GLADYS MARTINEZ | B35: Internet | C35: 1 Gig+ | D35: 235
A36: RAMON E PICHARDO | B36: Internet | C36: 1 Gig+ | D36: 235
A37: 3 Orders | D37: =SUM(D34:D36) -> 705
A39: PAYOUT SUMMARY
A40: Gross Commission | B40: 705
A41: Chargeback Deduction (from reserve) | B41: -300
A42: Reserve (15%) | B42: 0
A43: YTD Reserve Balance | B43: 3217.5
A44: Net Comp (after reserve) | B44: 705
A45: DD Fee | B45: -2.5
A46: PAYROLL | B46: 702.5
A47: ⚠ Chargeback: Victor Skarbnik (Maria Rico) — $300 from YTD reserve
A50: DANIEL DELEON
A51: Customer | B51: Service | C51: Tier | D51: Commission
A52: DAMIAN ARROYO | B52: Internet | C52: 150 Mbps | D52: 60
A53: 1 Orders | D53: =SUM(D52:D52) -> 60
A55: PAYOUT SUMMARY
A56: Gross Commission | B56: 60
A57: Reserve (15%) | B57: -9
A58: YTD Reserve Balance | B58: 63.75
A59: Net Comp (after reserve) | B59: 51
A60: Manager Override | B60: 30
A61: DD Fee | B61: -2.5
A62: PAYROLL | B62: 78.5
A63: ℹ $10 × 3 Jose team orders
A66: SEAN M. FISCHER
A67: Customer | B67: Service | C67: Tier | D67: Commission
A68: IVETTE VELEZQUEZ | B68: Internet | C68: 1 Gig+ | D68: 330
A69: SHANELLE TUCKER | B69: Internet | C69: 1 Gig+ | D69: 330
A70: 2 Orders | D70: =SUM(D68:D69) -> 660
A72: PAYOUT SUMMARY
A73: Gross Commission | B73: 660
A74: Reserve (15%) | B74: -99
A75: YTD Reserve Balance | B75: 99
A76: Net Comp (after reserve) | B76: 561
A77: SMF Override (Col E) | B77: 445
A78: DD Fee | B78: -2.5
A79: PAYROLL | B79: 1003.5
A80: ℹ Override on 300+ non-owner sales

Sheet 770015-Iron Crest - Maria R (3)
A1: Name | C1: Iron Crest - Maria Rico
A2: Production period | C2: 03/30/2026 - 04/05/2026
A3: Payday | C3: 04/10/2026
A4: Repcode | C4: 770015
A5: Office | C5: Iron Crest Solutions
A6: Team | C6: Iron Crest Solutions
A7: Company | C7: Power Marketing Group, LLC
A9: Summary
A11: Bonuses | B11: 390 | D11: Personal Meters Summary
A12: Chargeback | B12: -390 | D12: Status | E12: Sum
A13: Final pay: | B13: 0 | D13: Submitted | E13: 1
D14: Enrolled | E14: 0
D15: Rejected | E15: 1
D16: Pending | E16: 0
D17: Accepted rate | E17: 0%
D19: Office Meters Summary
D20: Status | E20: Sum
D21: Submitted | E21: 76
D22: Enrolled | E22: 39
D23: Rejected | E23: 37
D24: Pending | E24: 0
D25: Accepted rate | E25: 51%
A27: Additions And Deductions
A29: Additions
A30: Reason | B30: Amount
A31: OPTIMUM CHARGEBACK CREDIT (BUFFER) BUFFER REMAINING = 2913 [IRON CREST - MARIA RICO] | B31: 390
A34: Meters Details
A36: Office Meters Details
A37: Agent Name | B37: Customer Name | C37: Service Type | D37: Utility | E37: Client | F37: Date Sold | G37: Status | H37: Usage | I37: Rate | J37: Rejection Reason
A38: Iron Crest - Daniel DeLeon | B38: DAMIAN ARROYO | C38: Internet | D38: Lehigh Valley | E38: Astound | F38: 4/5/2026 | G38: Enrolled | H38: 150 | I38: 0
A39: Iron Crest - Jose Luis Molina | B39: RAMON E PICHARDO | C39: Internet | D39: Lehigh Valley | E39: Astound | F39: 4/5/2026 | G39: Enrolled | H39: 1500 | I39: 0
A40: Iron Crest - Jose Luis Molina | B40: CRISTAL MARMOL | C40: Internet | D40: Lehigh Valley | E40: Astound | F40: 4/4/2026 | G40: Enrolled | H40: 1500 | I40: 0
A41: Iron Crest - Jose Luis Molina | B41: GLADYS MARTINEZ | C41: Internet | D41: Lehigh Valley | E41: Astound | F41: 4/4/2026 | G41: Enrolled | H41: 1500 | I41: 0
A42: Iron Crest - Nicholas Marotta | B42: MAMADU JALLOH | C42: Internet | D42: New York | E42: Astound | F42: 4/5/2026 | G42: Enrolled | H42: 1000 | I42: 0
A43: Iron Crest - Nicholas Marotta | B43: ROBERT WOODARD | C43: Internet | D43: DC Metro | E43: Astound | F43: 4/3/2026 | G43: Enrolled | H43: 1000 | I43: 0
A44: Iron Crest - Nicholas Marotta | B44: CHRISTINE STERNER | C44: Internet | D44: Lehigh Valley | E44: Astound | F44: 4/3/2026 | G44: Enrolled | H44: 150 | I44: 0
A45: Iron Crest - Nicholas Marotta | B45: MONIQUE WHEELER | C45: Internet | D45: DC Metro | E45: Astound | F45: 4/2/2026 | G45: Enrolled | H45: 150 | I45: 0
A46: Iron Crest - Nikolas Fischer | B46: JOCEY VAGA | C46: Internet | D46: Lehigh Valley | E46: Astound | F46: 3/31/2026 | G46: Enrolled | H46: 1500 | I46: 0
A47: Iron Crest - Nikolas Fischer | B47: ERIC BELFORT | C47: Internet | D47: Lehigh Valley | E47: Astound | F47: 3/31/2026 | G47: Enrolled | H47: 1500 | I47: 0
A48: Iron Crest - Nikolas Fischer | B48: DEANGELO WILLIAMS | C48: Internet | D48: DC Metro | E48: Astound | F48: 4/2/2026 | G48: Enrolled | H48: 1500 | I48: 0
A49: Iron Crest - Nikolas Fischer | B49: ROSALINDA MORALES | C49: Internet | D49: Lehigh Valley | E49: Astound | F49: 3/30/2026 | G49: Enrolled | H49: 1500 | I49: 0
... A113: Iron Crest - Samuel Chapman | B113: CAROL GISCHEL | C113: Mobile | D113: Lehigh Valley | E113: Astound | F113: 4/1/2026 | G113: Customer changed mind | H113: 5 | I113: 0
A115: Meter Chargeback Details
A117: Personal Meter Chargeback Details
A118: Customer Name | B118: Service Type | C118: Utility | D118: Client | E118: Date Sold | F118: Status | G118: Usage | H118: Rate | I118: Rejection Reason
A119: Victor Skarbnik | B119: Internet | C119: N/A | D119: Optimum | E119: 2/25/2026 | F119: Chargeback | G119: 1500 | H119: -390

Sheet 770011-Iron Crest - Samuel  (3)
A1: Name | C1: Iron Crest - Samuel Chapman
A2: Production period | C2: 03/30/2026 - 04/05/2026
A3: Payday | C3: 04/10/2026
A4: Repcode | C4: 770011, 66048
A5: Office | C5: Iron Crest Solutions
A6: Team | C6: Iron Crest Solutions
A7: Company | C7: Power Marketing Group, LLC
A9: Summary
A11: Personal Meters | B11: 4,450.00 | D11: Personal Meters Summary
A12: Deduction | B12: -4,450.00 | D12: Status | E12: Sum
A13: Final pay: | B13: 0 | D13: Submitted | E13: 26
D14: Enrolled | E14: 15
D15: Rejected | E15: 11
D16: Pending | E16: 0
D17: Accepted rate | E17: 58%
D19: Office Meters Summary
D20: Status | E20: Sum
D21: Submitted | E21: 76
D22: Enrolled | E22: 39
D23: Rejected | E23: 37
D24: Pending | E24: 0
D25: Accepted rate | E25: 51%
A27: Additions And Deductions
D29: Deductions
D30: Reason | E30: Amount
D31: PAID TO IRON CREST, IRON CREST WILL PAY AGENT [IRON CREST - SAMUEL CHAPMAN] | E31: -4450
A34: Meters Details
A36: Personal Meters Details
A37: Customer Name | B37: Service Type | C37: Utility | D37: Client | E37: Date Sold | F37: Status | G37: Usage | H37: Rate | I37: Rejection Reason
A38: DIANA M GUTMAN | B38: Internet | C38: Lehigh Valley | D38: Astound | E38: 4/3/2026 | F38: Enrolled | G38: 1500 | H38: 400
A39: JANE M CHARLES | B39: Internet | C39: Lehigh Valley | D39: Astound | E39: 4/3/2026 | F39: Enrolled | G39: 1500 | H39: 400
A40: THERESA KUGELMAN | B40: Internet | C40: Lehigh Valley | D40: Astound | E40: 3/30/2026 | F40: Enrolled | G40: 1000 | H40: 370
A41: SHIRLEY MORRIS | B41: Internet | C41: Lehigh Valley | D41: Astound | E41: 4/2/2026 | F41: Enrolled | G41: 1000 | H41: 370
A42: RAPHAEL MARSH | B42: Internet | C42: Lehigh Valley | D42: Astound | E42: 4/3/2026 | F42: Enrolled | G42: 1000 | H42: 370
A43: JOANN PALESTRINI | B43: Internet | C43: Lehigh Valley | D43: Astound | E43: 4/1/2026 | F43: Enrolled | G43: 1000 | H43: 370
A44: JEROME HANEY | B44: Internet | C44: Lehigh Valley | D44: Astound | E44: 4/3/2026 | F44: Enrolled | G44: 1000 | H44: 370
A45: IRVIN SWEET | B45: Internet | C45: Lehigh Valley | D45: Astound | E45: 4/3/2026 | F45: Enrolled | G45: 1000 | H45: 370
A46: GLADYS LABOR | B46: Internet | C46: Lehigh Valley | D46: Astound | E46: 4/1/2026 | F46: Enrolled | G46: 1000 | H46: 370
A47: DARLINE LOCKETT | B47: Internet | C47: Lehigh Valley | D47: Astound | E47: 4/1/2026 | F47: Enrolled | G47: 1000 | H47: 370
A48: ANDREW WILLIAMS | B48: Internet | C48: Lehigh Valley | D48: Astound | E48: 4/1/2026 | F48: Enrolled | G48: 1000 | H48: 370
A49: EDWARD FLOYD | B49: Mobile | C49: Lehigh Valley | D49: Astound | E49: 4/3/2026 | F49: Enrolled | G49: 5 | H49: 65
... A63: CAROL GISCHEL | B63: Mobile | C63: Lehigh Valley | D63: Astound | E63: 4/1/2026 | F63: Customer changed mind | G63: 5 | H63: 0
A65: Office Meters Details
A66: Agent Name | B66: Customer Name | C66: Service Type | D66: Utility | E66: Client | F66: Date Sold | G66: Status | H66: Usage | I66: Rate | J66: Rejection Reason
A67: Iron Crest - Daniel DeLeon | B67: DAMIAN ARROYO | C67: Internet | D67: Lehigh Valley | E67: Astound | F67: 4/5/2026 | G67: Enrolled | H67: 150 | I67: 0
A68: Iron Crest - Jose Luis Molina | B68: RAMON E PICHARDO | C68: Internet | D68: Lehigh Valley | E68: Astound | F68: 4/5/2026 | G68: Enrolled | H68: 1500 | I68: 0
A69: Iron Crest - Jose Luis Molina | B69: CRISTAL MARMOL | C69: Internet | D69: Lehigh Valley | E69: Astound | F69: 4/4/2026 | G69: Enrolled | H69: 1500 | I69: 0
A70: Iron Crest - Jose Luis Molina | B70: GLADYS MARTINEZ | C70: Internet | D70: Lehigh Valley | E70: Astound | F70: 4/4/2026 | G70: Enrolled | H70: 1500 | I70: 0
A71: Iron Crest - Nicholas Marotta | B71: ROBERT WOODARD | C71: Internet | D71: DC Metro | E71: Astound | F71: 4/3/2026 | G71: Enrolled | H71: 1000 | I71: 0
A72: Iron Crest - Nicholas Marotta | B72: MAMADU JALLOH | C72: Internet | D72: New York | E72: Astound | F72: 4/5/2026 | G72: Enrolled | H72: 1000 | I72: 0
A73: Iron Crest - Nicholas Marotta | B73: MONIQUE WHEELER | C73: Internet | D73: DC Metro | E73: Astound | F73: 4/2/2026 | G73: Enrolled | H73: 150 | I73: 0
A74: Iron Crest - Nicholas Marotta | B74: CHRISTINE STERNER | C74: Internet | D74: Lehigh Valley | E74: Astound | F74: 4/3/2026 | G74: Enrolled | H74: 150 | I74: 0
A75: Iron Crest - Nikolas Fischer | B75: DEANGELO WILLIAMS | C75: Internet | D75: DC Metro | E75: Astound | F75: 4/2/2026 | G75: Enrolled | H75: 1500 | I75: 0
A76: Iron Crest - Nikolas Fischer | B76: ERIC BELFORT | C76: Internet | D76: Lehigh Valley | E76: Astound | F76: 3/31/2026 | G76: Enrolled | H76: 1500 | I76: 0
A77: Iron Crest - Nikolas Fischer | B77: SHANELLE TUCKER | C77: Internet | D77: Lehigh Valley | E77: Astound | F77: 4/1/2026 | G77: Enrolled | H77: 1500 | I77: 0
A78: Iron Crest - Nikolas Fischer | B78: ROSALINDA MORALES | C78: Internet | D78: Lehigh Valley | E78: Astound | F78: 3/30/2026 | G78: Enrolled | H78: 1500 | I78: 0
... A142: Iron Crest - Samuel Chapman | B142: SANDRA STROHL | C142: Mobile | D142: Lehigh Valley | E142: Astound | F142: 4/2/2026 | G142: Customer changed mind | H142: 5 | I142: 0

Sheet 66075-Iron Crest - Daniel D (2)
A1: Name | C1: Iron Crest - Daniel DeLeon
A2: Production period | C2: 03/30/2026 - 04/05/2026
A3: Payday | C3: 04/10/2026
A4: Repcode | C4: 66075
A5: Office | C5: Iron Crest Solutions
A6: Team | C6: Iron Crest Solutions
A7: Company | C7: Power Marketing Group, LLC
A9: Summary
A11: Personal Meters | B11: 200 | D11: Personal Meters Summary
A12: Deduction | B12: -200 | D12: Status | E12: Sum
A13: Final pay: | B13: 0 | D13: Submitted | E13: 2
D14: Enrolled | E14: 1
D15: Rejected | E15: 1
D16: Pending | E16: 0
D17: Accepted rate | E17: 50%
D19: Office Meters Summary
D20: Status | E20: Sum
D21: Submitted | E21: 76
D22: Enrolled | E22: 39
D23: Rejected | E23: 37
D24: Pending | E24: 0
D25: Accepted rate | E25: 51%
A27: Additions And Deductions
D29: Deductions
D30: Reason | E30: Amount
D31: PAID TO IRON CREST, IRON CREST WILL PAY AGENT [IRON CREST - DANIEL DELEON] | E31: -200
A34: Meters Details
A36: Personal Meters Details
A37: Customer Name | B37: Service Type | C37: Utility | D37: Client | E37: Date Sold | F37: Status | G37: Usage | H37: Rate | I37: Rejection Reason
A38: DAMIAN ARROYO | B38: Internet | C38: Lehigh Valley | D38: Astound | E38: 4/5/2026 | F38: Enrolled | G38: 150 | H38: 200
A39: ESMELYN BELTRE | B39: Internet | C39: Lehigh Valley | D39: Astound | E39: 4/3/2026 | F39: Order entered in error | G39: 1000 | H39: 0
A41: Office Meters Details
A42: Agent Name | B42: Customer Name | C42: Service Type | D42: Utility | E42: Client | F42: Date Sold | G42: Status | H42: Usage | I42: Rate | J42: Rejection Reason
A43: Iron Crest - Daniel DeLeon | B43: DAMIAN ARROYO | C43: Internet | D43: Lehigh Valley | E43: Astound | F43: 4/5/2026 | G43: Enrolled | H43: 150 | I43: 0
A44: Iron Crest - Jose Luis Molina | B44: CRISTAL MARMOL | C44: Internet | D44: Lehigh Valley | E44: Astound | F44: 4/4/2026 | G44: Enrolled | H44: 1500 | I44: 0
A45: Iron Crest - Jose Luis Molina | B45: GLADYS MARTINEZ | C45: Internet | D45: Lehigh Valley | E45: Astound | F45: 4/4/2026 | G45: Enrolled | H45: 1500 | I45: 0
A46: Iron Crest - Jose Luis Molina | B46: RAMON E PICHARDO | C46: Internet | D46: Lehigh Valley | E46: Astound | F46: 4/5/2026 | G46: Enrolled | H46: 1500 | I46: 0
A47: Iron Crest - Nicholas Marotta | B47: MAMADU JALLOH | C47: Internet | D47: New York | E47: Astound | F47: 4/5/2026 | G47: Enrolled | H47: 1000 | I47: 0
A48: Iron Crest - Nicholas Marotta | B48: ROBERT WOODARD | C48: Internet | D48: DC Metro | E48: Astound | F48: 4/3/2026 | G48: Enrolled | H48: 1000 | I48: 0
A49: Iron Crest - Nicholas Marotta | B49: CHRISTINE STERNER | C49: Internet | D49: Lehigh Valley | E49: Astound | F49: 4/3/2026 | G49: Enrolled | H49: 150 | I49: 0
A50: Iron Crest - Nicholas Marotta | B50: MONIQUE WHEELER | C50: Internet | D50: DC Metro | E50: Astound | F50: 4/2/2026 | G50: Enrolled | H50: 150 | I50: 0
A51: Iron Crest - Nikolas Fischer | B51: SHANELLE TUCKER | C51: Internet | D51: Lehigh Valley | E51: Astound | F51: 4/1/2026 | G51: Enrolled | H51: 1500 | I51: 0
A52: Iron Crest - Nikolas Fischer | B52: ROSALINDA MORALES | C52: Internet | D52: Lehigh Valley | E52: Astound | F52: 3/30/2026 | G52: Enrolled | H52: 1500 | I52: 0
A53: Iron Crest - Nikolas Fischer | B53: JOCEY VAGA | C53: Internet | D53: Lehigh Valley | E53: Astound | F53: 3/31/2026 | G53: Enrolled | H53: 1500 | I53: 0
A54: Iron Crest - Nikolas Fischer | B54: IVETTE VELEZQUEZ | C54: Internet | D54: Lehigh Valley | E54: Astound | F54: 3/31/2026 | G54: Enrolled | H54: 1500 | I54: 0
... A118: Iron Crest - Samuel Chapman | B118: LEROY GREEN | C118: Mobile | D118: Lehigh Valley | E118: Astound | F118: 3/31/2026 | G118: Customer changed mind | H118: 5 | I118: 0

Sheet 66062-Iron Crest - Jose Lui (3)
A1: Name | C1: Iron Crest - Jose Luis Molina
A2: Production period | C2: 03/30/2026 - 04/05/2026
A3: Payday | C3: 04/10/2026
A4: Repcode | C4: 66062
A5: Office | C5: Iron Crest Solutions
A6: Team | C6: Iron Crest Solutions
A7: Company | C7: Power Marketing Group, LLC
A9: Summary
A11: Personal Meters | B11: 1,200.00 | D11: Personal Meters Summary
A12: Deduction | B12: -1,200.00 | D12: Status | E12: Sum
A13: Final pay: | B13: 0 | D13: Submitted | E13: 3
D14: Enrolled | E14: 3
D15: Rejected | E15: 0
D16: Pending | E16: 0
D17: Accepted rate | E17: 100%
D19: Office Meters Summary
D20: Status | E20: Sum
D21: Submitted | E21: 76
D22: Enrolled | E22: 39
D23: Rejected | E23: 37
D24: Pending | E24: 0
D25: Accepted rate | E25: 51%
A27: Additions And Deductions
D29: Deductions
D30: Reason | E30: Amount
D31: PAID TO IRON CREST, IRON CREST WILL PAY AGENT [IRON CREST - JOSE LUIS MOLINA] | E31: -1200
A34: Meters Details
A36: Personal Meters Details
A37: Customer Name | B37: Service Type | C37: Utility | D37: Client | E37: Date Sold | F37: Status | G37: Usage | H37: Rate | I37: Rejection Reason
A38: RAMON E PICHARDO | B38: Internet | C38: Lehigh Valley | D38: Astound | E38: 4/5/2026 | F38: Enrolled | G38: 1500 | H38: 400
A39: GLADYS MARTINEZ | B39: Internet | C39: Lehigh Valley | D39: Astound | E39: 4/4/2026 | F39: Enrolled | G39: 1500 | H39: 400
A40: CRISTAL MARMOL | B40: Internet | C40: Lehigh Valley | D40: Astound | E40: 4/4/2026 | F40: Enrolled | G40: 1500 | H40: 400
A42: Office Meters Details
A43: Agent Name | B43: Customer Name | C43: Service Type | D43: Utility | E43: Client | F43: Date Sold | G43: Status | H43: Usage | I43: Rate | J43: Rejection Reason
A44: Iron Crest - Daniel DeLeon | B44: DAMIAN ARROYO | C44: Internet | D44: Lehigh Valley | E44: Astound | F44: 4/5/2026 | G44: Enrolled | H44: 150 | I44: 0
A45: Iron Crest - Jose Luis Molina | B45: CRISTAL MARMOL | C45: Internet | D45: Lehigh Valley | E45: Astound | F45: 4/4/2026 | G45: Enrolled | H45: 1500 | I45: 0
A46: Iron Crest - Jose Luis Molina | B46: GLADYS MARTINEZ | C46: Internet | D46: Lehigh Valley | E46: Astound | F46: 4/4/2026 | G46: Enrolled | H46: 1500 | I46: 0
A47: Iron Crest - Jose Luis Molina | B47: RAMON E PICHARDO | C47: Internet | D47: Lehigh Valley | E47: Astound | F47: 4/5/2026 | G47: Enrolled | H47: 1500 | I47: 0
A48: Iron Crest - Nicholas Marotta | B48: MAMADU JALLOH | C48: Internet | D48: New York | E48: Astound | F48: 4/5/2026 | G48: Enrolled | H48: 1000 | I48: 0
A49: Iron Crest - Nicholas Marotta | B49: ROBERT WOODARD | C49: Internet | D49: DC Metro | E49: Astound | F49: 4/3/2026 | G49: Enrolled | H49: 1000 | I49: 0
A50: Iron Crest - Nicholas Marotta | B50: MONIQUE WHEELER | C50: Internet | D50: DC Metro | E50: Astound | F50: 4/2/2026 | G50: Enrolled | H50: 150 | I50: 0
A51: Iron Crest - Nicholas Marotta | B51: CHRISTINE STERNER | C51: Internet | D51: Lehigh Valley | E51: Astound | F51: 4/3/2026 | G51: Enrolled | H51: 150 | I51: 0
A52: Iron Crest - Nikolas Fischer | B52: SHANELLE TUCKER | C52: Internet | D52: Lehigh Valley | E52: Astound | F52: 4/1/2026 | G52: Enrolled | H52: 1500 | I52: 0
A53: Iron Crest - Nikolas Fischer | B53: ROSALINDA MORALES | C53: Internet | D53: Lehigh Valley | E53: Astound | F53: 3/30/2026 | G53: Enrolled | H53: 1500 | I53: 0
A54: Iron Crest - Nikolas Fischer | B54: JOCEY VAGA | C54: Internet | D54: Lehigh Valley | E54: Astound | F54: 3/31/2026 | G54: Enrolled | H54: 1500 | I54: 0
A55: Iron Crest - Nikolas Fischer | B55: ERIC BELFORT | C55: Internet | D55: Lehigh Valley | E55: Astound | F55: 3/31/2026 | G55: Enrolled | H55: 1500 | I55: 0
... A119: Iron Crest - Samuel Chapman | B119: JOANN PALESTRINI | C119: Mobile | D119: Lehigh Valley | E119: Astound | F119: 3/31/2026 | G119: Order entered in error | H119: 5 | I119: 0

Sheet 66038-Iron Crest - Nicholas (3)
A1: Name | C1: Iron Crest - Nicholas Marotta
A2: Production period | C2: 03/30/2026 - 04/05/2026
A3: Payday | C3: 04/10/2026
A4: Repcode | C4: 66038, 770008
A5: Office | C5: Iron Crest Solutions
A6: Team | C6: Iron Crest Solutions
A7: Company | C7: Power Marketing Group, LLC
A9: Summary
A11: Personal Meters | B11: 1,140.00 | D11: Personal Meters Summary
A12: Deduction | B12: -1,140.00 | D12: Status | E12: Sum
A13: Final pay: | B13: 0 | D13: Submitted | E13: 17
D14: Enrolled | E14: 4
D15: Rejected | E15: 13
D16: Pending | E16: 0
D17: Accepted rate | E17: 24%
D19: Office Meters Summary
D20: Status | E20: Sum
D21: Submitted | E21: 76
D22: Enrolled | E22: 39
D23: Rejected | E23: 37
D24: Pending | E24: 0
D25: Accepted rate | E25: 51%
A27: Additions And Deductions
D29: Deductions
D30: Reason | E30: Amount
D31: PAID TO IRON CREST, IRON CREST WILL PAY AGENT [IRON CREST - NICHOLAS MAROTTA] | E31: -1140
A34: Meters Details
A36: Personal Meters Details
A37: Customer Name | B37: Service Type | C37: Utility | D37: Client | E37: Date Sold | F37: Status | G37: Usage | H37: Rate | I37: Rejection Reason
A38: ROBERT WOODARD | B38: Internet | C38: DC Metro | D38: Astound | E38: 4/3/2026 | F38: Enrolled | G38: 1000 | H38: 370
A39: MAMADU JALLOH | B39: Internet | C39: New York | D39: Astound | E39: 4/5/2026 | F39: Enrolled | G39: 1000 | H39: 370
A40: MONIQUE WHEELER | B40: Internet | C40: DC Metro | D40: Astound | E40: 4/2/2026 | F40: Enrolled | G40: 150 | H40: 200
A41: CHRISTINE STERNER | B41: Internet | C41: Lehigh Valley | D41: Astound | E41: 4/3/2026 | F41: Enrolled | G41: 150 | H41: 200
A42: BERNICE SANTIAGO | B42: Internet | C42: New York | D42: Astound | E42: 4/1/2026 | F42: Customer cancelled | G42: 1000 | H42: 0
A43: BROOKS NARONE | B43: Internet | C43: DC Metro | D43: Astound | E43: 4/2/2026 | F43: Credit policy requirements not met | G43: 1000 | H43: 0
A44: VERONICA GAFFORD | B44: Internet | C44: DC Metro | D44: Astound | E44: 4/2/2026 | F44: Customer changed mind | G44: 150 | H44: 0
A45: REGINALD MARTIN | B45: Internet | C45: DC Metro | D45: Astound | E45: 4/3/2026 | F45: Customer changed mind | G45: 150 | H45: 0
A46: FRED WALKER | B46: Internet | C46: DC Metro | D46: Astound | E46: 4/3/2026 | F46: Customer changed mind | G46: 150 | H46: 0
A47: BERNICE SANTIAGO | B47: Mobile | C47: New York | D47: Astound | E47: 4/3/2026 | F47: Customer changed mind | G47: 5 | H47: 0
A48: BROOKS NARONE | B48: Mobile | C48: DC Metro | D48: Astound | E48: 4/2/2026 | F48: Credit policy requirements not met | G48: 5 | H48: 0
A49: LEE THOMPSON | B49: Mobile | C49: Lehigh Valley | D49: Astound | E49: 4/4/2026 | F49: Trg canceled order entry error | G49: 5 | H49: 0
... A54: REGINALD MARTIN | B54: Mobile | C54: DC Metro | D54: Astound | E54: 4/3/2026 | F54: Customer changed mind | G54: 5 | H54: 0
A56: Office Meters Details
A57: Agent Name | B57: Customer Name | C57: Service Type | D57: Utility | E57: Client | F57: Date Sold | G57: Status | H57: Usage | I57: Rate | J57: Rejection Reason
A58: Iron Crest - Daniel DeLeon | B58: DAMIAN ARROYO | C58: Internet | D58: Lehigh Valley | E58: Astound | F58: 4/5/2026 | G58: Enrolled | H58: 150 | I58: 0
A59: Iron Crest - Jose Luis Molina | B59: RAMON E PICHARDO | C59: Internet | D59: Lehigh Valley | E59: Astound | F59: 4/5/2026 | G59: Enrolled | H59: 1500 | I59: 0
A60: Iron Crest - Jose Luis Molina | B60: GLADYS MARTINEZ | C60: Internet | D60: Lehigh Valley | E60: Astound | F60: 4/4/2026 | G60: Enrolled | H60: 1500 | I60: 0
A61: Iron Crest - Jose Luis Molina | B61: CRISTAL MARMOL | C61: Internet | D61: Lehigh Valley | E61: Astound | F61: 4/4/2026 | G61: Enrolled | H61: 1500 | I61: 0
A62: Iron Crest - Nicholas Marotta | B62: ROBERT WOODARD | C62: Internet | D62: DC Metro | E62: Astound | F62: 4/3/2026 | G62: Enrolled | H62: 1000 | I62: 0
A63: Iron Crest - Nicholas Marotta | B63: MAMADU JALLOH | C63: Internet | D63: New York | E63: Astound | F63: 4/5/2026 | G63: Enrolled | H63: 1000 | I63: 0
A64: Iron Crest - Nicholas Marotta | B64: MONIQUE WHEELER | C64: Internet | D64: DC Metro | E64: Astound | F64: 4/2/2026 | G64: Enrolled | H64: 150 | I64: 0
A65: Iron Crest - Nicholas Marotta | B65: CHRISTINE STERNER | C65: Internet | D65: Lehigh Valley | E65: Astound | F65: 4/3/2026 | G65: Enrolled | H65: 150 | I65: 0
A66: Iron Crest - Nikolas Fischer | B66: IVETTE VELEZQUEZ | C66: Internet | D66: Lehigh Valley | E66: Astound | F66: 3/31/2026 | G66: Enrolled | H66: 1500 | I66: 0
A67: Iron Crest - Nikolas Fischer | B67: ERIC BELFORT | C67: Internet | D67: Lehigh Valley | E67: Astound | F67: 3/31/2026 | G67: Enrolled | H67: 1500 | I67: 0
A68: Iron Crest - Nikolas Fischer | B68: DEANGELO WILLIAMS | C68: Internet | D68: DC Metro | E68: Astound | F68: 4/2/2026 | G68: Enrolled | H68: 1500 | I68: 0
A69: Iron Crest - Nikolas Fischer | B69: SHANELLE TUCKER | C69: Internet | D69: Lehigh Valley | E69: Astound | F69: 4/1/2026 | G69: Enrolled | H69: 1500 | I69: 0
... A133: Iron Crest - Samuel Chapman | B133: CAROL GISCHEL | C133: Mobile | D133: Lehigh Valley | E133: Astound | F133: 4/1/2026 | G133: Customer changed mind | H133: 5 | I133: 0

Sheet 66037-Iron Crest - Nikolas  (3)
A1: Name | C1: Iron Crest - Nikolas Fischer
A2: Production period | C2: 03/30/2026 - 04/05/2026
A3: Payday | C3: 04/10/2026
A4: Repcode | C4: 66037, 770007
A5: Office | C5: Iron Crest Solutions
A6: Team | C6: Iron Crest Solutions
A7: Company | C7: Power Marketing Group, LLC
A9: Summary
A11: Personal Meters | B11: 5,240.00 | D11: Personal Meters Summary
A12: Deduction | B12: -5,240.00 | D12: Status | E12: Sum
A13: Final pay: | B13: 0 | D13: Submitted | E13: 27
D14: Enrolled | E14: 16
D15: Rejected | E15: 11
D16: Pending | E16: 0
D17: Accepted rate | E17: 59%
D19: Office Meters Summary
D20: Status | E20: Sum
D21: Submitted | E21: 76
D22: Enrolled | E22: 39
D23: Rejected | E23: 37
D24: Pending | E24: 0
D25: Accepted rate | E25: 51%
A27: Additions And Deductions
D29: Deductions
D30: Reason | E30: Amount
D31: PAID TO IRON CREST, IRON CREST WILL PAY AGENT [IRON CREST - NIKOLAS FISCHER] | E31: -5240
A34: Meters Details
A36: Personal Meters Details
A37: Customer Name | B37: Service Type | C37: Utility | D37: Client | E37: Date Sold | F37: Status | G37: Usage | H37: Rate | I37: Rejection Reason
A38: ROSALINDA MORALES | B38: Internet | C38: Lehigh Valley | D38: Astound | E38: 3/30/2026 | F38: Enrolled | G38: 1500 | H38: 400
A39: DEANGELO WILLIAMS | B39: Internet | C39: DC Metro | D39: Astound | E39: 4/2/2026 | F39: Enrolled | G39: 1500 | H39: 400
A40: ERIC BELFORT | B40: Internet | C40: Lehigh Valley | D40: Astound | E40: 3/31/2026 | F40: Enrolled | G40: 1500 | H40: 400
A41: IVETTE VELEZQUEZ | B41: Internet | C41: Lehigh Valley | D41: Astound | E41: 3/31/2026 | F41: Enrolled | G41: 1500 | H41: 400
A42: JOCEY VAGA | B42: Internet | C42: Lehigh Valley | D42: Astound | E42: 3/31/2026 | F42: Enrolled | G42: 1500 | H42: 400
A43: SHANELLE TUCKER | B43: Internet | C43: Lehigh Valley | D43: Astound | E43: 4/1/2026 | F43: Enrolled | G43: 1500 | H43: 400
A44: MALIK JOHNSON | B44: Internet | C44: Lehigh Valley | D44: Astound | E44: 4/1/2026 | F44: Enrolled | G44: 1000 | H44: 370
A45: JESS RODRIGUEZ | B45: Internet | C45: Lehigh Valley | D45: Astound | E45: 4/3/2026 | F45: Enrolled | G45: 1000 | H45: 370
A46: EVY BOURGEIOS | B46: Internet | C46: Lehigh Valley | D46: Astound | E46: 4/5/2026 | F46: Enrolled | G46: 1000 | H46: 370
A47: ARCADIO DEJESUS | B47: Internet | C47: Lehigh Valley | D47: Astound | E47: 4/1/2026 | F47: Enrolled | G47: 1000 | H47: 370
A48: TAMEYA TAYLOR | B48: Internet | C48: DC Metro | D48: Astound | E48: 4/4/2026 | F48: Enrolled | G48: 1000 | H48: 370
A49: NAYSHA CLARKE | B49: Internet | C49: Philadelphia | D49: Astound | E49: 3/30/2026 | F49: Enrolled | G49: 1000 | H49: 370
... A64: LAWRENCE CHATMAN | B64: Mobile | C64: Lehigh Valley | D64: Astound | E64: 4/4/2026 | F64: Trg canceled order entry error | G64: 5 | H64: 0
A66: Office Meters Details
A67: Agent Name | B67: Customer Name | C67: Service Type | D67: Utility | E67: Client | F67: Date Sold | G67: Status | H67: Usage | I67: Rate | J67: Rejection Reason
A68: Iron Crest - Daniel DeLeon | B68: DAMIAN ARROYO | C68: Internet | D68: Lehigh Valley | E68: Astound | F68: 4/5/2026 | G68: Enrolled | H68: 150 | I68: 0
A69: Iron Crest - Jose Luis Molina | B69: RAMON E PICHARDO | C69: Internet | D69: Lehigh Valley | E69: Astound | F69: 4/5/2026 | G69: Enrolled | H69: 1500 | I69: 0
A70: Iron Crest - Jose Luis Molina | B70: GLADYS MARTINEZ | C70: Internet | D70: Lehigh Valley | E70: Astound | F70: 4/4/2026 | G70: Enrolled | H70: 1500 | I70: 0
A71: Iron Crest - Jose Luis Molina | B71: CRISTAL MARMOL | C71: Internet | D71: Lehigh Valley | E71: Astound | F71: 4/4/2026 | G71: Enrolled | H71: 1500 | I71: 0
A72: Iron Crest - Nicholas Marotta | B72: MAMADU JALLOH | C72: Internet | D72: New York | E72: Astound | F72: 4/5/2026 | G72: Enrolled | H72: 1000 | I72: 0
A73: Iron Crest - Nicholas Marotta | B73: ROBERT WOODARD | C73: Internet | D73: DC Metro | E73: Astound | F73: 4/3/2026 | G73: Enrolled | H73: 1000 | I73: 0
A74: Iron Crest - Nicholas Marotta | B74: CHRISTINE STERNER | C74: Internet | D74: Lehigh Valley | E74: Astound | F74: 4/3/2026 | G74: Enrolled | H74: 150 | I74: 0
A75: Iron Crest - Nicholas Marotta | B75: MONIQUE WHEELER | C75: Internet | D75: DC Metro | E75: Astound | F75: 4/2/2026 | G75: Enrolled | H75: 150 | I75: 0
A76: Iron Crest - Nikolas Fischer | B76: JOCEY VAGA | C76: Internet | D76: Lehigh Valley | E76: Astound | F76: 3/31/2026 | G76: Enrolled | H76: 1500 | I76: 0
A77: Iron Crest - Nikolas Fischer | B77: DEANGELO WILLIAMS | C77: Internet | D77: DC Metro | E77: Astound | F77: 4/2/2026 | G77: Enrolled | H77: 1500 | I77: 0
A78: Iron Crest - Nikolas Fischer | B78: ERIC BELFORT | C78: Internet | D78: Lehigh Valley | E78: Astound | F78: 3/31/2026 | G78: Enrolled | H78: 1500 | I78: 0
A79: Iron Crest - Nikolas Fischer | B79: IVETTE VELEZQUEZ | C79: Internet | D79: Lehigh Valley | E79: Astound | F79: 3/31/2026 | G79: Enrolled | H79: 1500 | I79: 0
... A143: Iron Crest - Samuel Chapman | B143: JOANN PALESTRINI | C143: Mobile | D143: Lehigh Valley | E143: Astound | F143: 3/31/2026 | G143: Order entered in error | H143: 5 | I143: 0

Sheet 220057-Iron Crest Solutions (3)
A1: Name | C1: Iron Crest Solutions
A2: Production period | C2: 03/30/2026 - 04/05/2026
A3: Payday | C3: 04/10/2026
A4: Repcode | C4: 220057
A5: Office | C5: Iron Crest Solutions
A6: Team | C6: Iron Crest Solutions
A7: Company | C7: Power Marketing Group, LLC
A9: Summary
A11: Bonuses | B11: 17,760.00
A12: Deduction | B12: -253.5
A13: Final pay: | B13: 17,506.50
A15: Additions And Deductions
A17: Additions | D17: Deductions
A18: Reason | B18: Amount | D18: Reason | E18: Amount
A19: MARCH OPTIMUM/ASTOUND INCENTIVE (174 INSTALLS X 15/INSTALL) [IRON CREST] | B19: 2610 | D19: MARCH ONBOARDING COSTS BALANCE OWED = 0 [IRON CREST SOLUTIONS] | E19: -253.5
A20: MARCH ASTOUND PA/MD/DC INCENTIVE (73 INSTALLS X 40/INSTALL) [IRON CREST] | B20: 2920
A21: FUNDING TO PAY IRON CREST AGENTS DIRECTLY [IRON CREST] | B21: 12230

Sheet 204489-Iron Crest - Richard Pla
A1: Name | C1: Iron Crest - Richard Placencia
A2: Production period | C2: 03/30/2026 - 04/05/2026
A3: Payday | C3: 04/10/2026
A4: Repcode | C4: 204489
A5: Office | C5: Iron Crest Solutions
A6: Team | C6: Iron Crest Solutions
A7: Company | C7: Power Marketing Group, LLC
A9: Summary
A11: Final pay: | B11: 0 | D11: Office Meters Summary
D12: Status | E12: Sum
D13: Submitted | E13: 76
D14: Enrolled | E14: 39
D15: Rejected | E15: 37
D16: Pending | E16: 0
D17: Accepted rate | E17: 51%
A21: Meters Details
A23: Office Meters Details
A24: Agent Name | B24: Customer Name | C24: Service Type | D24: Utility | E24: Client | F24: Date Sold | G24: Status | H24: Usage | I24: Rate | J24: Rejection Reason
A25: Iron Crest - Daniel DeLeon | B25: DAMIAN ARROYO | C25: Internet | D25: Lehigh Valley | E25: Astound | F25: 4/5/2026 | G25: Enrolled | H25: 150 | I25: 0
A26: Iron Crest - Jose Luis Molina | B26: GLADYS MARTINEZ | C26: Internet | D26: Lehigh Valley | E26: Astound | F26: 4/4/2026 | G26: Enrolled | H26: 1500 | I26: 0
A27: Iron Crest - Jose Luis Molina | B27: RAMON E PICHARDO | C27: Internet | D27: Lehigh Valley | E27: Astound | F27: 4/5/2026 | G27: Enrolled | H27: 1500 | I27: 0
A28: Iron Crest - Jose Luis Molina | B28: CRISTAL MARMOL | C28: Internet | D28: Lehigh Valley | E28: Astound | F28: 4/4/2026 | G28: Enrolled | H28: 1500 | I28: 0
A29: Iron Crest - Nicholas Marotta | B29: ROBERT WOODARD | C29: Internet | D29: DC Metro | E29: Astound | F29: 4/3/2026 | G29: Enrolled | H29: 1000 | I29: 0
A30: Iron Crest - Nicholas Marotta | B30: MAMADU JALLOH | C30: Internet | D30: New York | E30: Astound | F30: 4/5/2026 | G30: Enrolled | H30: 1000 | I30: 0
A31: Iron Crest - Nicholas Marotta | B31: MONIQUE WHEELER | C31: Internet | D31: DC Metro | E31: Astound | F31: 4/2/2026 | G31: Enrolled | H31: 150 | I31: 0
A32: Iron Crest - Nicholas Marotta | B32: CHRISTINE STERNER | C32: Internet | D32: Lehigh Valley | E32: Astound | F32: 4/3/2026 | G32: Enrolled | H32: 150 | I32: 0
A33: Iron Crest - Nikolas Fischer | B33: ROSALINDA MORALES | C33: Internet | D33: Lehigh Valley | E33: Astound | F33: 3/30/2026 | G33: Enrolled | H33: 1500 | I33: 0
A34: Iron Crest - Nikolas Fischer | B34: SHANELLE TUCKER | C34: Internet | D34: Lehigh Valley | E34: Astound | F34: 4/1/2026 | G34: Enrolled | H34: 1500 | I34: 0
A35: Iron Crest - Nikolas Fischer | B35: DEANGELO WILLIAMS | C35: Internet | D35: DC Metro | E35: Astound | F35: 4/2/2026 | G35: Enrolled | H35: 1500 | I35: 0
A36: Iron Crest - Nikolas Fischer | B36: ERIC BELFORT | C36: Internet | D36: Lehigh Valley | E36: Astound | F36: 3/31/2026 | G36: Enrolled | H36: 1500 | I36: 0
... A100: Iron Crest - Samuel Chapman | B100: CAROL GISCHEL | C100: Mobile | D100: Lehigh Valley | E100: Astound | F100: 4/1/2026 | G100: Customer changed mind | H100: 5 | I100: 0

Sheet Master Report (3)
A1: Sales list
A2: Repcode | B2: Account Number | C2: Customer Name | D2: Utility | E2: Service Type | F2: Date Sold | G2: Status | H2: Client | I2: State | J2: Usage
A3: 66037 | B3: 51280414 | C3: SHANELLE TUCKER | D3: Lehigh Valley | E3: Internet | F3: 4/1/2026 | G3: Accepted | H3: Astound | I3: N/A | J3: 1500
A4: 66048 | B4: 58051002 | C4: SHIRLEY MORRIS | D4: Lehigh Valley | E4: Internet | F4: 4/2/2026 | G4: Accepted | H4: Astound | I4: N/A | J4: 1000
A5: 66048 | B5: 58051002 | C5: SHIRLEY MORRIS | D5: Lehigh Valley | E5: TV | F5: 4/2/2026 | G5: Accepted | H5: Astound | I5: N/A | J5: 1
A6: 66037 | B6: 24377311 | C6: TAMEYA TAYLOR | D6: DC Metro | E6: Internet | F6: 4/4/2026 | G6: Accepted | H6: Astound | I6: N/A | J6: 1000
A7: 66048 | B7: 72181302 | C7: THERESA KUGELMAN | D7: Lehigh Valley | E7: Internet | F7: 3/30/2026 | G7: Accepted | H7: Astound | I7: N/A | J7: 1000
A8: 66048 | B8: 63714705 | C8: ANDREW WILLIAMS | D8: Lehigh Valley | E8: Internet | F8: 4/1/2026 | G8: Accepted | H8: Astound | I8: N/A | J8: 1000
A9: 66037 | B9: 39257304 | C9: ARCADIO DEJESUS | D9: Lehigh Valley | E9: Internet | F9: 4/1/2026 | G9: Accepted | H9: Astound | I9: N/A | J9: 1000
A10: 66038 | B10: 41727202 | C10: CHRISTINE STERNER | D10: Lehigh Valley | E10: Internet | F10: 4/3/2026 | G10: Accepted | H10: Astound | I10: N/A | J10: 150
A11: 66062 | B11: 70221217 | C11: CRISTAL MARMOL | D11: Lehigh Valley | E11: Internet | F11: 4/4/2026 | G11: Accepted | H11: Astound | I11: N/A | J11: 1500
A12: 66075 | B12: 79165002 | C12: DAMIAN ARROYO | D12: Lehigh Valley | E12: Internet | F12: 4/5/2026 | G12: Accepted | H12: Astound | I12: N/A | J12: 150
A13: 66048 | B13: 62281301 | C13: DARLINE LOCKETT | D13: Lehigh Valley | E13: Internet | F13: 4/1/2026 | G13: Accepted | H13: Astound | I13: N/A | J13: 1000
A14: 66037 | B14: 21746204 | C14: DEANGELO WILLIAMS | D14: DC Metro | E14: Internet | F14: 4/2/2026 | G14: Accepted | H14: Astound | I14: N/A | J14: 1500
... A79: 66048 | B79: 58051702 | C79: SANDRA STROHL | D79: Lehigh Valley | E79: Internet | F79: 4/2/2026 | G79: Customer changed mind | H79: Astound | I79: N/A | J79: 1000

Sheet 770015-Iron Crest - Maria R (2)
A1: Name | C1: Iron Crest - Maria Rico
A2: Production period | C2: 03/23/2026 - 03/29/2026
A3: Payday | C3: 04/03/2026
A4: Repcode | C4: 770015
A5: Office | C5: Iron Crest Solutions
A6: Team | C6: Iron Crest Solutions
A7: Company | C7: Power Marketing Group, LLC
A9: Summary
A11: Bonuses | B11: 390 | D11: Personal Meters Summary
A12: Chargeback | B12: -390 | D12: Status | E12: Sum
A13: Final pay: | B13: 0 | D13: Submitted | E13: 1
D14: Enrolled | E14: 0
D15: Rejected | E15: 1
D16: Pending | E16: 0
D17: Accepted rate | E17: 0%
A19: Additions And Deductions
A21: Additions
A22: Reason | B22: Amount
A23: OPTIMUM CHARGEBACK CREDIT (BUFFER) BUFFER REMAINING = 3303 [IRON CREST - MARIA RICO] | B23: 390
A26: Meter Chargeback Details
A28: Personal Meter Chargeback Details
A29: Customer Name | B29: Service Type | C29: Utility | D29: Client | E29: Date Sold | F29: Status | G29: Usage | H29: Rate | I29: Rejection Reason
A30: Alex Gonzalez | B30: Internet | C30: N/A | D30: Optimum | E30: 2/19/2026 | F30: Chargeback | G30: 1500 | H30: -390

Sheet 770011-Iron Crest - Samuel  (2)
A1: Name | C1: Iron Crest - Samuel Chapman
A2: Production period | C2: 03/23/2026 - 03/29/2026
A3: Payday | C3: 04/03/2026
A4: Repcode | C4: 770011, 66048
A5: Office | C5: Iron Crest Solutions
A6: Team | C6: Iron Crest Solutions
A7: Company | C7: Power Marketing Group, LLC
A9: Summary
A11: Personal Meters | B11: 4,070.00 | D11: Personal Meters Summary
A12: Deduction | B12: -4,070.00 | D12: Status | E12: Sum
A13: Final pay: | B13: 0 | D13: Submitted | E13: 24
D14: Enrolled | E14: 16
D15: Rejected | E15: 8
D16: Pending | E16: 0
D17: Accepted rate | E17: 67%
A19: Additions And Deductions
D21: Deductions
D22: Reason | E22: Amount
D23: PAID TO IRON CREST, IRON CREST WILL PAY AGENT [IRON CREST - SAMUEL CHAPMAN] | E23: -4070
A26: Meters Details
A28: Personal Meters Details
A29: Customer Name | B29: Service Type | C29: Utility | D29: Client | E29: Date Sold | F29: Status | G29: Usage | H29: Rate | I29: Rejection Reason
A30: SUZANNE MANIGO | B30: Internet | C30: Lehigh Valley | D30: Astound | E30: 3/26/2026 | F30: Enrolled | G30: 1000 | H30: 370
A31: ANTHONY FELLER | B31: Internet | C31: Lehigh Valley | D31: Astound | E31: 3/25/2026 | F31: Enrolled | G31: 1000 | H31: 370
A32: DEAN STEIN | B32: Internet | C32: Lehigh Valley | D32: Astound | E32: 3/29/2026 | F32: Enrolled | G32: 1000 | H32: 370
A33: JOAN PFEIFFER | B33: Internet | C33: Lehigh Valley | D33: Astound | E33: 3/27/2026 | F33: Enrolled | G33: 1000 | H33: 370
A34: MARIA AVILES | B34: Internet | C34: Lehigh Valley | D34: Astound | E34: 3/24/2026 | F34: Enrolled | G34: 1000 | H34: 370
A35: SHIRLEY A BINDER | B35: Internet | C35: Lehigh Valley | D35: Astound | E35: 3/27/2026 | F35: Enrolled | G35: 1000 | H35: 370
A36: AIDA RODRIQUEZ | B36: Internet | C36: Lehigh Valley | D36: Astound | E36: 3/27/2026 | F36: Enrolled | G36: 1000 | H36: 370
A37: SUSAN KEHM | B37: Internet | C37: Lehigh Valley | D37: Astound | E37: 3/25/2026 | F37: Enrolled | G37: 300 | H37: 270
A38: RICHARD LANCE | B38: Internet | C38: Lehigh Valley | D38: Astound | E38: 3/26/2026 | F38: Enrolled | G38: 300 | H38: 270
A39: ALFRED W WILLIAMS | B39: Internet | C39: Lehigh Valley | D39: Astound | E39: 3/25/2026 | F39: Enrolled | G39: 150 | H39: 200
A40: EILEEN KULP | B40: Internet | C40: Lehigh Valley | D40: Astound | E40: 3/27/2026 | F40: Enrolled | G40: 150 | H40: 200
A41: SULAIMAN HAQQ | B41: Internet | C41: Lehigh Valley | D41: Astound | E41: 3/26/2026 | F41: Enrolled | G41: 150 | H41: 200
... A53: NANCY SITLER | B53: Mobile | C53: Lehigh Valley | D53: Astound | E53: 3/26/2026 | F53: Customer changed mind | G53: 5 | H53: 0

Sheet 66094-Iron Crest - Monica Rico
A1: Name | C1: Iron Crest - Monica Rico
A2: Production period | C2: 03/23/2026 - 03/29/2026
A3: Payday | C3: 04/03/2026
A4: Repcode | C4: 66094
A5: Office | C5: Iron Crest Solutions
A6: Team | C6: Iron Crest Solutions
A7: Company | C7: Power Marketing Group, LLC
A9: Summary
A11: Personal Meters | B11: 400 | D11: Personal Meters Summary
A12: Deduction | B12: -400 | D12: Status | E12: Sum
A13: Final pay: | B13: 0 | D13: Submitted | E13: 2
D14: Enrolled | E14: 1
D15: Rejected | E15: 1
D16: Pending | E16: 0
D17: Accepted rate | E17: 50%
A19: Additions And Deductions
D21: Deductions
D22: Reason | E22: Amount
D23: PAID TO IRON CREST, IRON CREST WILL PAY AGENT [IRON CREST - MONICA RICO] | E23: -400
A26: Meters Details
A28: Personal Meters Details
A29: Customer Name | B29: Service Type | C29: Utility | D29: Client | E29: Date Sold | F29: Status | G29: Usage | H29: Rate | I29: Rejection Reason
A30: NICOLE KONKUS | B30: Internet | C30: Lehigh Valley | D30: Astound | E30: 3/27/2026 | F30: Enrolled | G30: 1500 | H30: 400
A31: AUBREY HALLINAN | B31: Internet | C31: Lehigh Valley | D31: Astound | E31: 3/26/2026 | F31: Customer req cancel via ivr | G31: 1000 | H31: 0

Sheet 66062-Iron Crest - Jose Lui (2)
A1: Name | C1: Iron Crest - Jose Luis Molina
A2: Production period | C2: 03/23/2026 - 03/29/2026
A3: Payday | C3: 04/03/2026
A4: Repcode | C4: 66062
A5: Office | C5: Iron Crest Solutions
A6: Team | C6: Iron Crest Solutions
A7: Company | C7: Power Marketing Group, LLC
A9: Summary
A11: Personal Meters | B11: 1,010.00 | D11: Personal Meters Summary
A12: Deduction | B12: -1,010.00 | D12: Status | E12: Sum
A13: Final pay: | B13: 0 | D13: Submitted | E13: 3
D14: Enrolled | E14: 3
D15: Rejected | E15: 0
D16: Pending | E16: 0
D17: Accepted rate | E17: 100%
A19: Additions And Deductions
D21: Deductions
D22: Reason | E22: Amount
D23: PAID TO IRON CREST, IRON CREST WILL PAY AGENT [IRON CREST - JOSE LUIS MOLINA] | E23: -1010
A26: Meters Details
A28: Personal Meters Details
A29: Customer Name | B29: Service Type | C29: Utility | D29: Client | E29: Date Sold | F29: Status | G29: Usage | H29: Rate | I29: Rejection Reason
A30: ANA D CRUZ | B30: Internet | C30: Lehigh Valley | D30: Astound | E30: 3/26/2026 | F30: Enrolled | G30: 1000 | H30: 370
A31: JULIA OLIVERA | B31: Internet | C31: Lehigh Valley | D31: Astound | E31: 3/26/2026 | F31: Enrolled | G31: 1000 | H31: 370
A32: VICTOR TORRES | B32: Internet | C32: Lehigh Valley | D32: Astound | E32: 3/24/2026 | F32: Enrolled | G32: 300 | H32: 270

Sheet 66060-Iron Crest - Cindy Re (2)
A1: Name | C1: Iron Crest - Cindy Reyes
A2: Production period | C2: 03/23/2026 - 03/29/2026
A3: Payday | C3: 04/03/2026
A4: Repcode | C4: 66060
A5: Office | C5: Iron Crest Solutions
A6: Team | C6: Iron Crest Solutions
A7: Company | C7: Power Marketing Group, LLC
A9: Summary
A11: Personal Meters | B11: 1,110.00 | D11: Personal Meters Summary
A12: Deduction | B12: -1,110.00 | D12: Status | E12: Sum
A13: Final pay: | B13: 0 | D13: Submitted | E13: 3
D14: Enrolled | E14: 3
D15: Rejected | E15: 0
D16: Pending | E16: 0
D17: Accepted rate | E17: 100%
A19: Additions And Deductions
D21: Deductions
D22: Reason | E22: Amount
D23: PAID TO IRON CREST, IRON CREST WILL PAY AGENT [IRON CREST - CINDY REYES] | E23: -1110
A26: Meters Details
A28: Personal Meters Details
A29: Customer Name | B29: Service Type | C29: Utility | D29: Client | E29: Date Sold | F29: Status | G29: Usage | H29: Rate | I29: Rejection Reason
A30: PATRICIA ALVAREZ | B30: Internet | C30: Lehigh Valley | D30: Astound | E30: 3/24/2026 | F30: Enrolled | G30: 1000 | H30: 370
A31: MARLYN OLIVO | B31: Internet | C31: Lehigh Valley | D31: Astound | E31: 3/26/2026 | F31: Enrolled | G31: 1000 | H31: 370
A32: YOLANDA CORPORAN | B32: Internet | C32: Lehigh Valley | D32: Astound | E32: 3/26/2026 | F32: Enrolled | G32: 1000 | H32: 370

Sheet 66038-Iron Crest - Nicholas (2)
A1: Name | C1: Iron Crest - Nicholas Marotta
A2: Production period | C2: 03/23/2026 - 03/29/2026
A3: Payday | C3: 04/03/2026
A4: Repcode | C4: 66038, 770008
A5: Office | C5: Iron Crest Solutions
A6: Team | C6: Iron Crest Solutions
A7: Company | C7: Power Marketing Group, LLC
A9: Summary
A11: Personal Meters | B11: 770 | D11: Personal Meters Summary
A12: Deduction | B12: -770 | D12: Status | E12: Sum
A13: Final pay: | B13: 0 | D13: Submitted | E13: 7
D14: Enrolled | E14: 3
D15: Rejected | E15: 4
D16: Pending | E16: 0
D17: Accepted rate | E17: 43%
A19: Additions And Deductions
D21: Deductions
D22: Reason | E22: Amount
D23: PAID TO IRON CREST, IRON CREST WILL PAY AGENT [IRON CREST - NICHOLAS MAROTTA] | E23: -770
A26: Meters Details
A28: Personal Meters Details
A29: Customer Name | B29: Service Type | C29: Utility | D29: Client | E29: Date Sold | F29: Status | G29: Usage | H29: Rate | I29: Rejection Reason
A30: BRIAN NETZGAR | B30: Internet | C30: Lehigh Valley | D30: Astound | E30: 3/28/2026 | F30: Enrolled | G30: 1000 | H30: 370
A31: STANLEY WILLAUER | B31: Internet | C31: Lehigh Valley | D31: Astound | E31: 3/27/2026 | F31: Enrolled | G31: 150 | H31: 200
A32: MARY ROMANSKY | B32: Internet | C32: Lehigh Valley | D32: Astound | E32: 3/27/2026 | F32: Enrolled | G32: 150 | H32: 200
A33: TASHA GREEN | B33: Internet | C33: Philadelphia | D33: Astound | E33: 3/25/2026 | F33: Customer req cancel via ivr | G33: 1000 | H33: 0
A34: STEVEN SMITH | B34: Internet | C34: Lehigh Valley | D34: Astound | E34: 3/27/2026 | F34: Customer changed mind | G34: 150 | H34: 0
A35: BRAD HENDERSHOT | B35: Mobile | C35: Lehigh Valley | D35: Astound | E35: 3/28/2026 | F35: Trg canceled order entry error | G35: 5 | H35: 0
A36: TASHA GREEN | B36: Mobile | C36: Philadelphia | D36: Astound | E36: 3/25/2026 | F36: Customer req cancel via ivr | G36: 5 | H36: 0

Sheet 66037-Iron Crest - Nikolas  (2)
A1: Name | C1: Iron Crest - Nikolas Fischer
A2: Production period | C2: 03/23/2026 - 03/29/2026
A3: Payday | C3: 04/03/2026
A4: Repcode | C4: 66037, 770007
A5: Office | C5: Iron Crest Solutions
A6: Team | C6: Iron Crest Solutions
A7: Company | C7: Power Marketing Group, LLC
A9: Summary
A11: Personal Meters | B11: 270 | D11: Personal Meters Summary
A12: Bonuses | B12: 350 | D12: Status | E12: Sum
A13: Chargeback | B13: -350 | D13: Submitted | E13: 15
A14: Deduction | B14: -270 | D14: Enrolled | E14: 1
A15: Final pay: | B15: 0 | D15: Rejected | E15: 14
D16: Pending | E16: 0
D17: Accepted rate | E17: 7%
A19: Additions And Deductions
A21: Additions | D21: Deductions
A22: Reason | B22: Amount | D22: Reason | E22: Amount
A23: OPTIMUM CHARGEBACK CREDIT (BUFFER) BUFFER REMAINING = 236 [IRON CREST - NIKOLAS FISCHER] | B23: 350 | D23: PAID TO IRON CREST, IRON CREST WILL PAY AGENT [IRON CREST - NIKOLAS FISCHER] | E23: -270
A26: Meters Details
A28: Personal Meters Details
A29: Customer Name | B29: Service Type | C29: Utility | D29: Client | E29: Date Sold | F29: Status | G29: Usage | H29: Rate | I29: Rejection Reason
A30: JESUS CORDERO | B30: Internet | C30: Lehigh Valley | D30: Astound | E30: 3/26/2026 | F30: Enrolled | G30: 300 | H30: 270
A31: VALERIE VALDEZ | B31: Internet | C31: Lehigh Valley | D31: Astound | E31: 3/27/2026 | F31: Customer cancel at door | G31: 1000 | H31: 0
A32: TYRONE SMITH | B32: Internet | C32: Philadelphia | D32: Astound | E32: 3/26/2026 | F32: Credit policy requirements not met | G32: 1000 | H32: 0
A33: REGGIE SMITH | B33: Internet | C33: Philadelphia | D33: Astound | E33: 3/26/2026 | F33: Customer changed mind | G33: 1000 | H33: 0
A34: EGYPT JACKSON | B34: Internet | C34: Philadelphia | D34: Astound | E34: 3/26/2026 | F34: Credit policy requirements not met | G34: 1000 | H34: 0
A35: JOHN WALLACE | B35: Internet | C35: Lehigh Valley | D35: Astound | E35: 3/24/2026 | F35: Customer changed mind | G35: 150 | H35: 0
A36: SUSAN KEHM | B36: Internet | C36: Lehigh Valley | D36: Astound | E36: 3/24/2026 | F36: Incomplete order | G36: 150 | H36: 0
A37: BEVERLY DEL SANTRO | B37: Mobile | C37: Lehigh Valley | D37: Astound | E37: 3/28/2026 | F37: Trg canceled order entry error | G37: 5 | H37: 0
A38: DAWN STERNER | B38: Mobile | C38: Lehigh Valley | D38: Astound | E38: 3/28/2026 | F38: Trg canceled order entry error | G38: 5 | H38: 0
A39: EGYPT JACKSON | B39: Mobile | C39: Philadelphia | D39: Astound | E39: 3/26/2026 | F39: Fraud/theft | G39: 5 | H39: 0
A40: GARY MCQUAGGE | B40: Mobile | C40: Lehigh Valley | D40: Astound | E40: 3/23/2026 | F40: Trg canceled order entry error | G40: 5 | H40: 0
A41: JOHN WALLACE | B41: Mobile | C41: Lehigh Valley | D41: Astound | E41: 3/24/2026 | F41: Customer cancel on pre-call | G41: 5 | H41: 0
... A43: TYRONE SMITH | B43: Mobile | C43: Philadelphia | D43: Astound | E43: 3/26/2026 | F43: Fraud/theft | G43: 5 | H43: 0
A45: Meter Chargeback Details
A47: Personal Meter Chargeback Details
A48: Customer Name | B48: Service Type | C48: Utility | D48: Client | E48: Date Sold | F48: Status | G48: Usage | H48: Rate | I48: Rejection Reason
A49: John Pressher | B49: Internet | C49: N/A | D49: Optimum | E49: 12/2/2025 | F49: Chargeback | G49: 1000 | H49: -350

Sheet 220057-Iron Crest Solutions (2)
A1: Name | C1: Iron Crest Solutions
A2: Production period | C2: 03/23/2026 - 03/29/2026
A3: Payday | C3: 04/03/2026
A4: Repcode | C4: 220057
A5: Office | C5: Iron Crest Solutions
A6: Team | C6: Iron Crest Solutions
A7: Company | C7: Power Marketing Group, LLC
A9: Summary
A11: Bonuses | B11: 7,630.00
A12: Final pay: | B12: 7,630.00
A14: Additions And Deductions
A16: Additions
A17: Reason | B17: Amount
A18: FUNDING TO PAY IRON CREST AGENTS DIRECTLY [IRON CREST] | B18: 7630

Sheet Master Report (2)
A1: Sales list
A2: Repcode | B2: Account Number | C2: Customer Name | D2: Utility | E2: Service Type | F2: Date Sold | G2: Status | H2: Client | I2: State | J2: Usage
A3: 66048 | B3: 56743303 | C3: AIDA RODRIQUEZ | D3: Lehigh Valley | E3: Internet | F3: 3/27/2026 | G3: Accepted | H3: Astound | I3: N/A | J3: 1000
A4: 66048 | B4: 56743303 | C4: AIDA RODRIQUEZ | D4: Lehigh Valley | E4: TV | F4: 3/27/2026 | G4: Accepted | H4: Astound | I4: N/A | J4: 1
A5: 66048 | B5: 66482601 | C5: RICHARD LANCE | D5: Lehigh Valley | E5: Internet | F5: 3/26/2026 | G5: Accepted | H5: Astound | I5: N/A | J5: 300
A6: 66048 | B6: 66482601 | C6: RICHARD LANCE | D6: Lehigh Valley | E6: TV | F6: 3/26/2026 | G6: Accepted | H6: Astound | I6: N/A | J6: 1
A7: 66048 | B7: 72961504 | C7: SUSAN KEHM | D7: Lehigh Valley | E7: Internet | F7: 3/25/2026 | G7: Accepted | H7: Astound | I7: N/A | J7: 300
A8: 66048 | B8: 72961504 | C8: SUSAN KEHM | D8: Lehigh Valley | E8: TV | F8: 3/25/2026 | G8: Accepted | H8: Astound | I8: N/A | J8: 1
A9: 66048 | B9: 65004602 | C9: SUZANNE MANIGO | D9: Lehigh Valley | E9: Internet | F9: 3/26/2026 | G9: Accepted | H9: Astound | I9: N/A | J9: 1000
A10: 66048 | B10: 65004602 | C10: SUZANNE MANIGO | D10: Lehigh Valley | E10: TV | F10: 3/26/2026 | G10: Accepted | H10: Astound | I10: N/A | J10: 1
A11: 66094 | B11: 75300501 | C11: NICOLE KONKUS | D11: Lehigh Valley | E11: Internet | F11: 3/27/2026 | G11: Accepted | H11: Astound | I11: N/A | J11: 1500
A12: 66062 | B12: 50026019 | C12: ANA D CRUZ | D12: Lehigh Valley | E12: Internet | F12: 3/26/2026 | G12: Accepted | H12: Astound | I12: N/A | J12: 1000
A13: 66048 | B13: 72964302 | C13: ANTHONY FELLER | D13: Lehigh Valley | E13: Internet | F13: 3/25/2026 | G13: Accepted | H13: Astound | I13: N/A | J13: 1000
A14: 66038 | B14: 66289408 | C14: BRIAN NETZGAR | D14: Lehigh Valley | E14: Internet | F14: 3/28/2026 | G14: Accepted | H14: Astound | I14: N/A | J14: 1000
... A57: 66037 | B57: 44541605 | C57: TYRONE SMITH | D57: Philadelphia | E57: Mobile | F57: 3/26/2026 | G57: Fraud/theft | H57: Astound | I57: N/A | J57: 5

Sheet Comp Plan
A1: Speed | B1: Rep | C1: Leader | D1: Dan/Other Manager | E1: SMF Director | F1: Stefano- Operations | G1: Joei- Accounting | H1: Iron Crest Executive Pay | I1: Iron Crest Profit | J1: Elevated Personal Sales (Stefano/Andrew/Sean)
A2: 50 Mbps | B2: 25 | C2: 25 | D2: 25 | E2: 0 | F2: 0 | G2: 0 | H2: 100 | I2: 75
A3: 150 Mbps | B3: 60 | C3: 60 | D3: 60 | E3: 0 | F3: 10 | G3: 5 | H3: 200 | I3: 125 | J3: 145
A4: 300 Mbps | B4: 125 | C4: 130 | D4: 135 | E4: 25 | F4: 10 | G4: 5 | H4: 270 | I4: 95 | J4: 200
A5: 600 Mbps | B5: 135 | C5: 145 | D5: 155 | E5: 30 | F5: 10 | G5: 5 | H5: 300 | I5: 100 | J5: 230
A6: 1 Gig | B6: 200 | C6: 210 | D6: 220 | E6: 30 | F6: 10 | G6: 5 | H6: 370 | I6: 105 | J6: 300
A7: 1 Gig+ | B7: 225 | C7: 235 | D7: 245 | E7: 35 | F7: 10 | G7: 5 | H7: 400 | I7: 105 | J7: 330
A8: Unlm. mobile | B8: 40 | C8: 45 | D8: 45 | E8: 0 | F8: 0 | G8: 0 | H8: 65 | I8: 20 | J8: 55
A9: TV | B9: 40 | C9: 50 | D9: 50 | E9: 0 | F9: 0 | G9: 0 | H9: 85 | I9: 35 | J9: 55

Sheet 3.25.26
A2: Commissions 3/25/26
A3: PMG PAYOUT | B3: 10465
A4: Spreadseet confirmation
A5: Totals: Column B/H/N | B5: =SUM(B19+H19+M22) -> 10465
A7: Iron Crest Employee | B7: Gross Commissions | C7: Connects | D7: Deductions | E7: Commission After Deductions | F7: Reserve-15% | G7: YTD Reserve Balance | H7: NET BONUS | I7: Stefano Override | J7: Joei Override | K7: Sean Override | L7: Dan Override | M7: Iron Crest Overrides | N7: NET COMP | O7: Direct Deposit Fee | P7: PAYROLL TOTAL | Q7: Comments
A8: Nik Fischer | B8: 2660 | C8: 7 | E8: 0 | H8: 120 | N8: =B8-I8-J8 -> 2660 | O8: 0 | P8: =SUM(N8-O8) -> 2660
A9: Nick Marotta | B9: 2660 | C9: 9 | E9: 0 | H9: 40 | N9: =B9-I9-J9 -> 2660 | O9: 0 | P9: =SUM(N9-O9) -> 2660
A10: Sam Chapman | B10: 215 | C10: 4 | D10: 550 | F10: 114.75 | G10: 773.75 | I10: 40 | J10: 20 | K10: 95 | L10: 0 | M10: 305 | N10: 650.25 | O10: 2.5 | P10: =SUM(N10-O10) -> 647.75 | Q10: *Incurred Chargebacks and was upside down. Took his commission to pay out of his reserve. Iron Crest received -190 chargeback from Sam.
A11: Jose Molina | B11: 2160 | C11: 9 | E11: 2160 | F11: 0 | G11: 3817.5 | H11: 80 | I11: 90 | J11: 45 | K11: 285 | L11: 90 | M11: 720 | N11: =B11-F11 -> 2160 | O11: 2.5 | P11: =SUM(N11-O11) -> 2157.5
A12: Cindy Reyes | B12: 0 | F12: 0 | G12: 0 | H12: 40 | N12: =B12-F12 -> 0 | P12: =SUM(N12-O12) -> 0
A13: Nicholas Digiamo | B13: 0 | F13: =B13*15% -> 0 | G13: 77.25 | N13: =B13-F13 -> 0 | P13: =SUM(N13-O13) -> 0
A14: Jeffrey Scott | B14: 0 | F14: =B14*15% -> 0 | G14: 33.75 | N14: =B14-F14 -> 0 | P14: 0
A15: Stefano Fischer | F15: =B15*15% -> 0 | N15: =B18-F18 -> 0 | P15: 320
A16: Joei Ruffino | B16: 0 | F16: 0 | P16: 160
A17: Dan DeLeon | B17: 365 | C17: 3 | E17: 365 | F17: =B17*15% -> 54.75 | G17: 54.75 | I17: 30 | J17: 15 | K17: 35 | L17: 0 | M17: 355 | N17: =B17-F17 -> 310.25 | O17: 2.5 | P17: =SUM(N17-O17) -> 307.75
A18: SMF | P18: 415
A19: TOTAL | B19: =SUM(B8:B18) -> 8060 | C19: =SUM(C8:C18) -> 32 | D19: =SUM(D8:D18) -> 550 | E19: =SUM(E8:E18) -> 2525 | F19: =SUM(F10:F18) -> 169.5 | G19: =SUM(G10:G18) -> 4757 | H19: =SUM(H8:H18) -> 280 | I19: =SUM(I8:I18) -> 160 | J19: =SUM(J8:J18) -> 80 | K19: =SUM(K8:K18) -> 415 | L19: =SUM(L8:L18) -> 90 | M19: =SUM(M8:M18) -> 1380 | N19: =SUM(N8:N18) -> 8440.5 | O19: =SUM(O8:O18) -> 7.5 | P19: =SUM(P8:P18) -> 9328
A20: Operations Override (Joei/Stefano) | I20: 160 | J20: 80 | K20: 44444 | M20: =SUM(I20+J20) -> 240
A21: Iron Crest Net Overrides | M21: =M19-M20 -> 1140
A22: Total Overrides Paid | M22: =SUM(I19+J19+K19+L19+M19) -> 2125
A24: IRON CREST ORDERS
A25: Cust Name | B25: Service | C25: Rep | D25: Provider | E25: Amount
A26: ALFONZO SMITH | B26: Internet | C26: SR3 | D26: Astound | E26: 400
A27: ANTHONY GONZALEZ | B27: Internet | C27: SR3 | D27: Astound | E27: 370
A28: DAMIAN CASTRO | B28: Internet | C28: SR3 | D28: Astound | E28: 200
A29: DONALD PATE | B29: Internet | C29: SR3 | D29: Astound | E29: 200
A30: DONALD WILLIAMS | B30: Internet | C30: SR3 | D30: Astound | E30: 200
A31: EDUARDO QUINONES | B31: Internet | C31: SR3 | D31: Astound | E31: 370
A32: GREG STATON | B32: Internet | C32: SR3 | D32: Astound | E32: 370 | G32: =SUM(E26:E41) -> 4600
A33: HILLIARD ODOM | B33: Internet | C33: SR3 | D33: Astound | E33: 200 | G33: =SUM(E42:E45) -> 720
A34: JACQUELINE LUNDY | B34: Internet | C34: SR3 | D34: Astound | E34: 370
A35: JAMES QUIER | B35: Internet | C35: SR3 | D35: Astound | E35: 370
A36: JOSE MILLAN | B36: Internet | C36: SR3 | D36: Astound | E36: 400
A37: KELLY VARGAS | B37: Internet | C37: SR3 | D37: Astound | E37: 400
A38: LUIS CHEVEREZ | B38: Internet | C38: SR3 | D38: Astound | E38: 400
A39: LUIS CHEVEREZ | B39: TV | C39: SR3 | D39: Astound | E39: 85
A40: NASHAE ALLMOND | B40: Internet | C40: SR3 | D40: Astound | E40: 200
A41: SAM IRBY | B41: Mobile | C41: SR3 | D41: Astound | E41: 65
A42: BINTA BAH | B42: Internet | C42: SR3 | D42: Astound | E42: 370
A43: CYNTHIA DEAN | B43: Internet | C43: SR3 | D43: Astound | E43: 200
A44: VERNA POUGH | B44: Mobile | C44: SR3 | D44: Astound | E44: 65
A45: JACQUELINE LUNDY | B45: TV | C45: SR3 | D45: Astound | E45: 85
E46: =SUM(E26:E45) -> 5320

Sheet 770015-Iron Crest - Maria Rico
A1: Name | C1: Iron Crest - Maria Rico
A2: Production period | C2: 03/16/2026 - 03/22/2026
A3: Payday | C3: 03/27/2026
A4: Repcode | C4: 770015
A5: Office | C5: Iron Crest Solutions
A6: Team | C6: Iron Crest Solutions
A7: Company | C7: Power Marketing Group, LLC
A9: Summary
A11: Personal Meters | B11: 1,170.00 | D11: Personal Meters Summary
A12: Deduction | B12: -1,170.00 | D12: Status | E12: Sum
A13: Final pay: | B13: 0 | D13: Submitted | E13: 3
D14: Enrolled | E14: 3
D15: Rejected | E15: 0
D16: Pending | E16: 0
D17: Accepted rate | E17: 100%
A19: Additions And Deductions
D21: Deductions
D22: Reason | E22: Amount
D23: PAID TO IRON CREST, IRON CREST WILL PAY AGENT [IRON CREST - MARIA RICO] | E23: -1170
A26: Meters Details
A28: Personal Meters Details
A29: Customer Name | B29: Service Type | C29: Utility | D29: Client | E29: Date Sold | F29: Status | G29: Usage | H29: Rate | I29: Rejection Reason
A30: Jowie Ocasio | B30: Internet | C30: N/A | D30: Optimum | E30: 3/22/2026 | F30: Enrolled | G30: 1500 | H30: 390
A31: Miguel Mejia | B31: Internet | C31: N/A | D31: Optimum | E31: 3/21/2026 | F31: Enrolled | G31: 1500 | H31: 390
A32: Esteban Alvarez | B32: Internet | C32: N/A | D32: Optimum | E32: 3/22/2026 | F32: Enrolled | G32: 1500 | H32: 390

Sheet 3.29.26
A2: Commissions 3/29/26
A3: PMG PAYOUT | B3: 7630
A4: Spreadsheet confirmation | B4: =SUM(B20+H20+M23) -> 7630
A5: Totals: Column B/H/N | B5: =SUM(B20+H20+M23) -> 7630
A7: Iron Crest Employee | B7: Gross Commissions | C7: Connects | D7: Deductions | E7: Commission After Deductions | F7: Reserve-15% | G7: YTD Reserve Balance | H7: NET BONUS | I7: Stefano Override | J7: Joei Override | K7: Sean Override | L7: Dan Override | M7: Iron Crest Overrides | N7: NET COMP | O7: Direct Deposit Fee | P7: PAYROLL TOTAL | Q7: Comments
A8: Nik Fischer | B8: 720 | C8: 2 | E8: 0 | H8: 0 | N8: =B8-I8-J8 -> 720 | O8: 0 | P8: =N8-O8 -> 720 | Q8: Owners pool: Nik $270 + Nick $770 + Monica $400 = $1,440 / 2 = $720 each
A9: Nick Marotta | B9: 720 | C9: 3 | E9: 0 | H9: 0 | N9: =B9-I9-J9 -> 720 | O9: 0 | P9: =N9-O9 -> 720
A10: Sam Chapman | B10: 2110 | C10: 12 | D10: 0 | E10: 2110 | F10: 316.5 | G10: 1090.25 | H10: 0 | I10: 120 | J10: 60 | K10: 260 | L10: 0 | M10: 1520 | N10: 1793.5 | O10: 2.5 | P10: 1791
A11: Jose Molina | B11: 1180 | C11: 6 | D11: 300 | E11: 1180 | F11: 0 | G11: 3517.5 | H11: 0 | I11: 60 | J11: 30 | K11: 175 | L11: 60 | M11: 615 | N11: =B11-F11 -> 1180 | O11: 2.5 | P11: =N11-O11 -> 1177.5 | Q11: Jose 3 + Cindy 3 = 6 connects. Monica Konkus moved to owner pool.
A12: Cindy Reyes | B12: 0 | F12: 0 | G12: 0 | M12: 0 | N12: =B12-F12 -> 0 | P12: =N12-O12 -> 0
A13: Monica Rico | B13: 0 | F13: 0 | G13: 0 | N13: =B13-F13 -> 0 | P13: =N13-O13 -> 0 | Q13: New - Leader under Jose/Dan
A14: Nicholas Digiamo | B14: 0 | F14: =B14*15% -> 0 | G14: 77.25 | N14: =B14-F14 -> 0 | P14: 0
A15: Jeffrey Scott | B15: 0 | F15: =B15*15% -> 0 | G15: 33.75 | N15: =B15-F15 -> 0 | P15: 0
A16: Stefano Fischer | P16: =I20+I21 -> 230
A17: Joei Ruffino | B17: 0 | P17: =J20+J21 -> 115
A18: Dan DeLeon | B18: 0 | C18: 0 | E18: 0 | F18: 0 | G18: 54.75 | I18: 0 | J18: 0 | K18: 0 | L18: 0 | M18: 0 | N18: =B18-F18 -> 0 | O18: 2.5 | P18: =N18-O18+L20 -> 57.5 | Q18: $70 override from Jose's 7 team sales ($10 × 7)
A19: Sean M. Fischer | P19: =K20 -> 435
A20: TOTAL | B20: =SUM(B8:B19) -> 4730 | C20: =SUM(C8:C19) -> 23 | D20: =SUM(D8:D19) -> 300 | E20: =SUM(E8:E19) -> 3290 | F20: =SUM(F8:F19) -> 316.5 | G20: =SUM(G8:G19) -> 4773.5 | H20: =SUM(H8:H19) -> 0 | I20: =SUM(I8:I19) -> 180 | ... P20: =SUM(P8:P19) -> 5246
A21: Operations Override (Joei/Stefano) | I21: 50 | J21: 25 | M21: =SUM(I21+J21) -> 75
A22: Iron Crest Net Overrides | M22: =M20-M21 -> 2060
A23: Total Overrides Paid | M23: =I20+J20+K20+L20+M20 -> 2900
A25: IRON CREST ORDERS
A26: Cust Name | B26: Service | C26: Rep | D26: Provider | E26: Amount
A27: JESUS CORDERO | B27: Internet | C27: Nik Fischer | D27: Astound | E27: 270 | F27: =SUM(E27:E53) -> 7630
A28: BRIAN NETZGAR | B28: Internet | C28: Nick Marotta | D28: Astound | E28: 370
A29: STANLEY WILLAUER | B29: Internet | C29: Nick Marotta | D29: Astound | E29: 200
A30: MARY ROMANSKY | B30: Internet | C30: Nick Marotta | D30: Astound | E30: 200
A31: SUZANNE MANIGO | B31: Internet | C31: Sam Chapman | D31: Astound | E31: 370
A32: ANTHONY FELLER | B32: Internet | C32: Sam Chapman | D32: Astound | E32: 370
A33: DEAN STEIN | B33: Internet | C33: Sam Chapman | D33: Astound | E33: 370
A34: JOAN PFEIFFER | B34: Internet | C34: Sam Chapman | D34: Astound | E34: 370
A35: MARIA AVILES | B35: Internet | C35: Sam Chapman | D35: Astound | E35: 370
A36: SHIRLEY A BINDER | B36: Internet | C36: Sam Chapman | D36: Astound | E36: 370
A37: AIDA RODRIQUEZ | B37: Internet | C37: Sam Chapman | D37: Astound | E37: 370
A38: SUSAN KEHM | B38: Internet | C38: Sam Chapman | D38: Astound | E38: 270
A39: RICHARD LANCE | B39: Internet | C39: Sam Chapman | D39: Astound | E39: 270
... A53: NICOLE KONKUS | B53: Internet | C53: Monica (66094) | D53: Astound | E53: 400

Sheet Owner Report - 3.29.26
A1: IRON CREST SOLUTIONS
A2: Weekly Payout Report — WE 3/29/2026
A3: Production Period: 03/23/2026 – 03/29/2026 | Payday: 04/03/2026
A5: WEEKLY P&L SNAPSHOT
A6: PMG Funding Received | B6: 7630
A7: Less: Rep/Leader Commissions | B7: ='3.29.26'!B20 -> 4730
A8: Less: Stefano Override | B8: ='3.29.26'!I20+'3.29.26'!I21 -> 230
A9: Less: Joei Override | B9: ='3.29.26'!J20+'3.29.26'!J21 -> 115
A10: Less: SMF (Sean) Override | B10: ='3.29.26'!K20 -> 435
A11: Less: Dan Override | B11: ='3.29.26'!L20 -> 60
A12: Less: Direct Deposit Fees | B12: ='3.29.26'!O20 -> 7.5
A13: Less: Chargeback Loss (IC portion) | B13: 90 | C13: See chargeback detail (Row 78)
A14: IRON CREST NET PROFIT | B14: =B6-B7-B8-B9-B10-B11-B12-B13 -> 1962.5
A16: OWNER COMPENSATION
A17: Nik Fischer Sales | B17: 2 orders | C17: 670 | D17: JESUS CORDERO (300), NICOLE KONKUS (1G+ via Monica)
A18: Nick Marotta Sales | B18: 3 orders | C18: 770 | D18: NETZGAR (1G), WILLAUER (150), ROMANSKY (150)
A19: Combined Owner Pool | C19: =C17+C18 -> 1440
A20: 50/50 Split → Each Owner Receives | C20: =C19/2 -> 720
A21: Iron Crest Net Profit (above) | C21: =B14 -> 1962.5
A22: TOTAL OWNER INCOME (each) | C22: =C20+(C21/2) -> 1701.25
A24: PAYROLL BREAKDOWN
A25: Employee | B25: Gross Comm. | C25: Connects | D25: Reserve (15%) | E25: YTD Reserve | F25: NET COMP | H25: DD Fee | I25: PAYROLL
A26: Nik Fischer | B26: ='3.29.26'!B8 -> 720 | C26: ='3.29.26'!C8 -> 2 | D26: N/A | E26: N/A | F26: ='3.29.26'!N8 -> 720 | H26: ='3.29.26'!O8 -> 0 | I26: ='3.29.26'!P8 -> 720
A27: Nick Marotta | B27: ='3.29.26'!B9 -> 720 | C27: ='3.29.26'!C9 -> 3 | D27: N/A | E27: N/A | F27: ='3.29.26'!N9 -> 720 | H27: ='3.29.26'!O9 -> 0 | I27: ='3.29.26'!P9 -> 720
A28: Sam Chapman | B28: ='3.29.26'!B10 -> 2110 | C28: 12 | D28: ='3.29.26'!F10 -> 316.5 | E28: ='3.29.26'!G10 -> 1090.25 | F28: ='3.29.26'!N10 -> 1793.5 | H28: ='3.29.26'!O10 -> 2.5 | I28: ='3.29.26'!P10 -> 1791
A29: Jose Molina (team) | B29: ='3.29.26'!B11 -> 1180 | C29: ='3.29.26'!C11 -> 6 | D29: ='3.29.26'!F11 -> 0 | E29: ='3.29.26'!G11 -> 3517.5 | F29: ='3.29.26'!N11 -> 1180 | H29: ='3.29.26'!O11 -> 2.5 | I29: ='3.29.26'!P11 -> 1177.5
A30: Dan DeLeon | B30: ='3.29.26'!B18 -> 0 | C30: ='3.29.26'!C18 -> 0 | D30: ='3.29.26'!F18 -> 0 | E30: ='3.29.26'!G18 -> 54.75 | F30: ='3.29.26'!N18+'3.29.26'!L20 -> 60 | H30: ='3.29.26'!O18 -> 2.5 | I30: ='3.29.26'!P18 -> 57.5
A31: Stefano Fischer | F31: ='3.29.26'!P16 -> 230 | I31: ='3.29.26'!P16 -> 230
A32: Joei Ruffino | F32: ='3.29.26'!P17 -> 115 | I32: ='3.29.26'!P17 -> 115
A33: Sean M. Fischer | F33: ='3.29.26'!P19 -> 435 | I33: ='3.29.26'!P19 -> 435
A34: TOTAL PAYROLL | I34: =SUM(I26:I33) -> 5246
A36: OVERRIDE DETAIL
A37: Override Recipient | B37: Sam's Orders | C37: Jose Team Orders | D37: Owner Orders | E37: TOTAL
A38: Stefano Fischer | B38: 120 | C38: 60 | D38: 50 | E38: =SUM(B38:D38) -> 230
A39: Joei Ruffino | B39: 60 | C39: 30 | D39: 25 | E39: =SUM(B39:D39) -> 115
A40: SMF (Sean) | B40: 260 | C40: 175 | D40: 0 | E40: =SUM(B40:D40) -> 435
A41: Dan DeLeon | B41: 0 | C41: 60 | D41: 0 | E41: =SUM(B41:D41) -> 60
A42: Iron Crest Profit | B42: 1520 | C42: 615 | D42: 0 | E42: =SUM(B42:D42) -> 2135
A43: TOTAL PER GROUP | B43: =SUM(B38:B42) -> 1960 | C43: =SUM(C38:C42) -> 940 | D43: =SUM(D38:D42) -> 75 | E43: =SUM(E38:E42) -> 2975
A45: ALL ACCEPTED ORDERS (27)
A46: Customer | B46: Service | C46: Tier | D46: Sold By | E46: Exec Rate | F46: IC Profit | G46: Rep Comm
A47: AIDA RODRIQUEZ | B47: Internet | C47: 1 Gig | D47: Sam Chapman | E47: 370 | F47: 115 | G47: 210
A48: SUZANNE MANIGO | B48: Internet | C48: 1 Gig | D48: Sam Chapman | E48: 370 | F48: 115 | G48: 210
A49: ANTHONY FELLER | B49: Internet | C49: 1 Gig | D49: Sam Chapman | E49: 370 | F49: 115 | G49: 210
A50: DEAN STEIN | B50: Internet | C50: 1 Gig | D50: Sam Chapman | E50: 370 | F50: 115 | G50: 210
A51: JOAN PFEIFFER | B51: Internet | C51: 1 Gig | D51: Sam Chapman | E51: 370 | F51: 115 | G51: 210
A52: MARIA AVILES | B52: Internet | C52: 1 Gig | D52: Sam Chapman | E52: 370 | F52: 115 | G52: 210
A53: SHIRLEY A BINDER | B53: Internet | C53: 1 Gig | D53: Sam Chapman | E53: 370 | F53: 115 | G53: 210
A54: RICHARD LANCE | B54: Internet | C54: 300 Mbps | D54: Sam Chapman | E54: 270 | F54: 100 | G54: 130
A55: SUSAN KEHM | B55: Internet | C55: 300 Mbps | D55: Sam Chapman | E55: 270 | F55: 100 | G55: 130
A56: ALFRED W WILLIAMS | B56: Internet | C56: 150 Mbps | D56: Sam Chapman | E56: 200 | F56: 125 | G56: 60
A57: EILEEN KULP | B57: Internet | C57: 150 Mbps | D57: Sam Chapman | E57: 200 | F57: 125 | G57: 60
A58: SULAIMAN HAQQ | B58: Internet | C58: 150 Mbps | D58: Sam Chapman | E58: 200 | F58: 125 | G58: 60
... A73: MARY ROMANSKY | B73: Internet | C73: 150 Mbps | D73: Nick Marotta | E73: 200 | F73: 0 | G73: 200
A74: TOTALS | B74: 27 orders | E74: =SUM(E47:E73) -> 7630 | F74: =SUM(F47:F73) -> 2135 | G74: =SUM(G47:G73) -> 4730
A76: CHARGEBACKS
A77: Customer | B77: Original Rep | C77: Provider | D77: Tier | E77: PMG Chargeback | F77: Rep Reserve Hit | H77: IC Net Loss
A78: Alex Gonzalez | B78: Maria Rico (→ Jose) | C78: Optimum | D78: 1 Gig+ | E78: -390 | F78: -300 | H78: =E78-F78 -> -90
A79: John Pressher | B79: Nik Fischer (Owner) | C79: Optimum | D79: 1 Gig | E79: -350 | F79: N/A | H79: 0
A80: TOTAL CHARGEBACK IMPACT | E80: =SUM(E78:E79) -> -740 | F80: -300 | H80: =H78+H79 -> -90

Sheet Rep - Sam Chapman 3.29
A1: IRON CREST SOLUTIONS
A2: Commission Statement — Sam Chapman
A3: Week Ending: 3/29/2026 | Payday: 04/03/2026
A5: YOUR ACCEPTED ORDERS
A6: Customer | B6: Service | C6: Tier | D6: Your Commission
A7: AIDA RODRIQUEZ | B7: Internet | C7: 1 Gig | D7: 210
A8: SUZANNE MANIGO | B8: Internet | C8: 1 Gig | D8: 210
A9: ANTHONY FELLER | B9: Internet | C9: 1 Gig | D9: 210
A10: DEAN STEIN | B10: Internet | C10: 1 Gig | D10: 210
A11: JOAN PFEIFFER | B11: Internet | C11: 1 Gig | D11: 210
A12: MARIA AVILES | B12: Internet | C12: 1 Gig | D12: 210
A13: SHIRLEY A BINDER | B13: Internet | C13: 1 Gig | D13: 210
A14: RICHARD LANCE | B14: Internet | C14: 300 Mbps | D14: 130
A15: SUSAN KEHM | B15: Internet | C15: 300 Mbps | D15: 130
A16: ALFRED W WILLIAMS | B16: Internet | C16: 150 Mbps | D16: 60
A17: EILEEN KULP | B17: Internet | C17: 150 Mbps | D17: 60
A18: SULAIMAN HAQQ | B18: Internet | C18: 150 Mbps | D18: 60
... A22: RICHARD LANCE | B22: TV | C22: TV | D22: 50
A23: TOTAL | B23: 16 orders | D23: =SUM(D7:D22) -> 2110
A25: COMPENSATION SUMMARY
A26: Gross Commission | B26: =D23 -> 2110
A27: Less: Reserve (15%) | B27: =-B26*0.15 -> -316.5
A28: Less: DD Fee | B28: -2.5
A29: NET COMP | B29: =B26+B27+B28 -> 1791
A30: YTD Reserve Balance | B30: 1090.25
A32: No chargebacks this period.

Sheet Rep - Jose Team 3.29
A1: IRON CREST SOLUTIONS
A2: Commission Statement — Jose Molina (Team)
A3: Week Ending: 3/29/2026 | Payday: 04/03/2026
A4: Includes: Jose, Cindy Reyes, Maria Rico (treated as one unit)
A6: YOUR ACCEPTED ORDERS
A7: Customer | B7: Sold By | C7: Tier | D7: Commission
A8: ANA D CRUZ | B8: Jose | C8: 1 Gig | D8: 210
A9: JULIA OLIVERA | B9: Jose | C9: 1 Gig | D9: 210
A10: VICTOR TORRES | B10: Jose | C10: 300 Mbps | D10: 130
A11: PATRICIA ALVAREZ | B11: Cindy | C11: 1 Gig | D11: 210
A12: MARLYN OLIVO | B12: Cindy | C12: 1 Gig | D12: 210
A13: YOLANDA CORPORAN | B13: Cindy | C13: 1 Gig | D13: 210
A14: TOTAL | B14: 6 orders | D14: =SUM(D8:D13) -> 1180
A16: CHARGEBACKS
A17: Customer | B17: Original Seller | C17: Tier | D17: Reserve Hit
A18: Alex Gonzalez | B18: Maria Rico | C18: 1 Gig+ | D18: -300
A21: COMPENSATION SUMMARY
A22: Gross Commission | B22: =D14 -> 1180
A23: Less: Reserve (15%) | B23: 0
A24: Chargeback (from reserve) | B24: -300
A25: Less: DD Fee | B25: -2.5
A26: NET COMP | B26: =B22+B23+B25 -> 1177.5
A27: YTD Reserve Balance | B27: 3517.5

Sheet Rep - Nik Fischer 3.29
A1: IRON CREST SOLUTIONS
A2: Commission Statement — Nik Fischer
A3: Week Ending: 3/29/2026 | Payday: 04/03/2026
A5: YOUR ACCEPTED ORDERS
A6: Customer | B6: Service | C6: Tier | D6: Your Commission
A7: NICOLE KONKUS | B7: Internet | C7: 1 Gig+ | D7: 400
A8: JESUS CORDERO | B8: Internet | C8: 300 Mbps | D8: 270
A9: TOTAL | B9: 2 orders | D9: =SUM(D7:D8) -> 670
A11: CHARGEBACKS
A12: Customer | B12: Provider | C12: Tier | D12: Impact
A13: John Pressher | B13: Optimum | C13: 1 Gig | D13: $0 (buffer covered)
A15: COMPENSATION SUMMARY
A16: Gross Commission | B16: =D9 -> 670
A17: Reserve: | B17: N/A (Owner)
A18: Less: DD Fee | B18: 0
A19: NET COMP (50/50 pool split) | B19: 720

Sheet Rep - Nick Marotta 3.29
A1: IRON CREST SOLUTIONS
A2: Commission Statement — Nick Marotta
A3: Week Ending: 3/29/2026 | Payday: 04/03/2026
A5: YOUR ACCEPTED ORDERS
A6: Customer | B6: Service | C6: Tier | D6: Your Commission
A7: BRIAN NETZGAR | B7: Internet | C7: 1 Gig | D7: 370
A8: STANLEY WILLAUER | B8: Internet | C8: 150 Mbps | D8: 200
A9: MARY ROMANSKY | B9: Internet | C9: 150 Mbps | D9: 200
A10: TOTAL | B10: 3 orders | D10: =SUM(D7:D9) -> 770
A12: COMPENSATION SUMMARY
A13: Gross Commission | B13: =D10 -> 770
A14: Reserve: | B14: N/A (Owner)
A15: Less: DD Fee | B15: 0
A16: NET COMP (50/50 pool split) | B16: 720
A18: No chargebacks this period.

Sheet 770011-Iron Crest - Samuel Chap
A1: Name | C1: Iron Crest - Samuel Chapman
A2: Production period | C2: 03/16/2026 - 03/22/2026
A3: Payday | C3: 03/27/2026
A4: Repcode | C4: 770011, 66048
A5: Office | C5: Iron Crest Solutions
A6: Team | C6: Iron Crest Solutions
A7: Company | C7: Power Marketing Group, LLC
A9: Summary
A11: Personal Meters | B11: 1,415.00 | D11: Personal Meters Summary
A12: Chargeback | B12: -740 | D12: Status | E12: Sum
A13: Deduction | B13: -675 | D13: Submitted | E13: 21
A14: Final pay: | B14: 0 | D14: Enrolled | E14: 5
D15: Rejected | E15: 16
D16: Pending | E16: 0
D17: Accepted rate | E17: 24%
A19: Additions And Deductions
D21: Deductions
D22: Reason | E22: Amount
D23: PAID TO IRON CREST, IRON CREST WILL PAY AGENT [IRON CREST - SAMUEL CHAPMAN] | E23: -675
A26: Meters Details
A28: Personal Meters Details
A29: Customer Name | B29: Service Type | C29: Utility | D29: Client | E29: Date Sold | F29: Status | G29: Usage | H29: Rate | I29: Rejection Reason
A30: Monica Diaz | B30: Internet | C30: N/A | D30: Optimum | E30: 3/19/2026 | F30: Enrolled | G30: 1500 | H30: 390
A31: WOODROW W DUNN | B31: Internet | C31: New York | D31: Astound | E31: 3/18/2026 | F31: Enrolled | G31: 1000 | H31: 370
A32: ROBERTO COMPOS | B32: Internet | C32: New York | D32: Astound | E32: 3/19/2026 | F32: Enrolled | G32: 1000 | H32: 370
A33: RACHEL HOLLOWAY | B33: Internet | C33: New York | D33: Astound | E33: 3/19/2026 | F33: Enrolled | G33: 150 | H33: 200
A34: WOODROW W DUNN | B34: TV | C34: New York | D34: Astound | E34: 3/18/2026 | F34: Enrolled | G34: 1 | H34: 85
A35: ZENAIDA CARABELLO SIME | B35: Internet | C35: Lehigh Valley | D35: Astound | E35: 3/21/2026 | F35: Customer changed mind | G35: 1500 | H35: 0
A36: CHRISTOPHE STEWART | B36: Internet | C36: New York | D36: Astound | E36: 3/18/2026 | F36: Customer changed mind | G36: 1000 | H36: 0
A37: DONNA CHARLES | B37: Internet | C37: New York | D37: Astound | E37: 3/20/2026 | F37: Customer changed mind | G37: 1000 | H37: 0
A38: DALANDA BAH | B38: Internet | C38: New York | D38: Astound | E38: 3/20/2026 | F38: Customer changed mind | G38: 1000 | H38: 0
A39: FATOUMATA BARRY | B39: Internet | C39: New York | D39: Astound | E39: 3/18/2026 | F39: Customer changed mind | G39: 1000 | H39: 0
A40: IBRAHIM JALLOH | B40: Internet | C40: New York | D40: Astound | E40: 3/18/2026 | F40: Customer changed mind | G40: 1000 | H40: 0
A41: MURDENA ROPER | B41: Internet | C41: New York | D41: Astound | E41: 3/19/2026 | F41: Customer changed mind | G41: 1000 | H41: 0
... A48: FATOUMATA BARRY | B48: Mobile | C48: New York | D48: Astound | E48: 3/18/2026 | F48: Customer changed mind | G48: 5 | H48: 0
A50: Meter Chargeback Details
A52: Personal Meter Chargeback Details
A53: Customer Name | B53: Service Type | C53: Utility | D53: Client | E53: Date Sold | F53: Status | G53: Usage | H53: Rate | I53: Rejection Reason
A54: Earline Ford | B54: Internet | C54: N/A | D54: Optimum | E54: 3/9/2026 | F54: Chargeback | G54: 1500 | H54: -390
A55: Robert Imbriaco | B55: Internet | C55: N/A | D55: Optimum | E55: 2/13/2026 | F55: Chargeback | G55: 1000 | H55: -350

Sheet 66075-Iron Crest - Daniel DeLeo
A1: Name | C1: Iron Crest - Daniel DeLeon
A2: Production period | C2: 03/16/2026 - 03/22/2026
A3: Payday | C3: 03/27/2026
A4: Repcode | C4: 66075
A5: Office | C5: Iron Crest Solutions
A6: Team | C6: Iron Crest Solutions
A7: Company | C7: Power Marketing Group, LLC
A9: Summary
A11: Personal Meters | B11: 800 | D11: Personal Meters Summary
A12: Deduction | B12: -800 | D12: Status | E12: Sum
A13: Final pay: | B13: 0 | D13: Submitted | E13: 3
D14: Enrolled | E14: 3
D15: Rejected | E15: 0
D16: Pending | E16: 0
D17: Accepted rate | E17: 100%
A19: Additions And Deductions
D21: Deductions
D22: Reason | E22: Amount
D23: PAID TO IRON CREST, IRON CREST WILL PAY AGENT [IRON CREST - DANIEL DELEON] | E23: -800
A26: Meters Details
A28: Personal Meters Details
A29: Customer Name | B29: Service Type | C29: Utility | D29: Client | E29: Date Sold | F29: Status | G29: Usage | H29: Rate | I29: Rejection Reason
A30: GEORGE CABRERA | B30: Internet | C30: Lehigh Valley | D30: Astound | E30: 3/18/2026 | F30: Enrolled | G30: 1500 | H30: 400
A31: GUILLERMO CORONADO | B31: Internet | C31: Lehigh Valley | D31: Astound | E31: 3/17/2026 | F31: Enrolled | G31: 150 | H31: 200
A32: MAXIMO MARTINEZ | B32: Internet | C32: Lehigh Valley | D32: Astound | E32: 3/21/2026 | F32: Enrolled | G32: 150 | H32: 200

Sheet 66062-Iron Crest - Jose Luis Mo
A1: Name | C1: Iron Crest - Jose Luis Molina
A2: Production period | C2: 03/16/2026 - 03/22/2026
A3: Payday | C3: 03/27/2026
A4: Repcode | C4: 66062
A5: Office | C5: Iron Crest Solutions
A6: Team | C6: Iron Crest Solutions
A7: Company | C7: Power Marketing Group, LLC
A9: Summary
A11: Personal Meters | B11: 1,850.00 | D11: Personal Meters Summary
A12: Bonuses | B12: 80 | D12: Status | E12: Sum
A13: Deduction | B13: -1,930.00 | D13: Submitted | E13: 6
A14: Final pay: | B14: 0 | D14: Enrolled | E14: 5
D15: Rejected | E15: 1
D16: Pending | E16: 0
D17: Accepted rate | E17: 83%
A19: Additions And Deductions
A21: Additions | D21: Deductions
A22: Reason | B22: Amount | D22: Reason | E22: Amount
A23: ASTOUND 3/19 - 3/22 BLITZ - JULIO CRUZ [IRON CREST - JOSE LUIS MOLINA] | B23: 40 | D23: PAID TO IRON CREST, IRON CREST WILL PAY AGENT [IRON CREST - JOSE LUIS MOLINA] | E23: -1930
A24: ASTOUND 3/19 - 3/22 BLITZ - YOSMERI ACOSTA [IRON CREST - JOSE LUIS MOLINA] | B24: 40
A27: Meters Details
A29: Personal Meters Details
A30: Customer Name | B30: Service Type | C30: Utility | D30: Client | E30: Date Sold | F30: Status | G30: Usage | H30: Rate | I30: Rejection Reason
A31: EDISON MAMALLACTA | B31: Internet | C31: Lehigh Valley | D31: Astound | E31: 3/17/2026 | F31: Enrolled | G31: 1000 | H31: 370
A32: JULIO CRUZ | B32: Internet | C32: Lehigh Valley | D32: Astound | E32: 3/19/2026 | F32: Enrolled | G32: 1000 | H32: 370
A33: YOSMERI ACOSTA | B33: Internet | C33: Lehigh Valley | D33: Astound | E33: 3/21/2026 | F33: Enrolled | G33: 1000 | H33: 370
A34: MIGUELINA MARTINEZ | B34: Internet | C34: Lehigh Valley | D34: Astound | E34: 3/18/2026 | F34: Enrolled | G34: 1000 | H34: 370
A35: MARISOL CRUZ | B35: Internet | C35: Lehigh Valley | D35: Astound | E35: 3/20/2026 | F35: Enrolled | G35: 1000 | H35: 370
A36: PATRICIA ALVAREZ | B36: Internet | C36: Lehigh Valley | D36: Astound | E36: 3/18/2026 | F36: Order entered in error | G36: 1000 | H36: 0

Sheet 66060-Iron Crest - Cindy Reyes
A1: Name | C1: Iron Crest - Cindy Reyes
A2: Production period | C2: 03/16/2026 - 03/22/2026
A3: Payday | C3: 03/27/2026
A4: Repcode | C4: 66060
A5: Office | C5: Iron Crest Solutions
A6: Team | C6: Iron Crest Solutions
A7: Company | C7: Power Marketing Group, LLC
A9: Summary
A11: Personal Meters | B11: 370 | D11: Personal Meters Summary
A12: Bonuses | B12: 40 | D12: Status | E12: Sum
A13: Deduction | B13: -410 | D13: Submitted | E13: 1
A14: Final pay: | B14: 0 | D14: Enrolled | E14: 1
D15: Rejected | E15: 0
D16: Pending | E16: 0
D17: Accepted rate | E17: 100%
A19: Additions And Deductions
A21: Additions | D21: Deductions
A22: Reason | B22: Amount | D22: Reason | E22: Amount
A23: ASTOUND 3/19 - 3/22 BLITZ - MATILDE SOTO [IRON CREST - CINDY ORDONEZ REYES] | B23: 40 | D23: PAID TO IRON CREST, IRON CREST WILL PAY AGENT [IRON CREST - CINDY REYES] | E23: -410
A26: Meters Details
A28: Personal Meters Details
A29: Customer Name | B29: Service Type | C29: Utility | D29: Client | E29: Date Sold | F29: Status | G29: Usage | H29: Rate | I29: Rejection Reason
A30: MATILDE SOTO | B30: Internet | C30: Lehigh Valley | D30: Astound | E30: 3/21/2026 | F30: Enrolled | G30: 1000 | H30: 370

Sheet 66038-Iron Crest - Nicholas Mar
A1: Name | C1: Iron Crest - Nicholas Marotta
A2: Production period | C2: 03/16/2026 - 03/22/2026
A3: Payday | C3: 03/27/2026
A4: Repcode | C4: 66038, 770008
A5: Office | C5: Iron Crest Solutions
A6: Team | C6: Iron Crest Solutions
A7: Company | C7: Power Marketing Group, LLC
A9: Summary
A11: Personal Meters | B11: 2,260.00 | D11: Personal Meters Summary
A12: Bonuses | B12: 375 | D12: Status | E12: Sum
A13: Chargeback | B13: -335 | D13: Submitted | E13: 16
A14: Deduction | B14: -2,300.00 | D14: Enrolled | E14: 9
A15: Final pay: | B15: 0 | D15: Rejected | E15: 7
D16: Pending | E16: 0
D17: Accepted rate | E17: 56%
A19: Additions And Deductions
A21: Additions | D21: Deductions
A22: Reason | B22: Amount | D22: Reason | E22: Amount
A23: ASTOUND 3/19 - 3/22 BLITZ - JAMES QUIER [IRON CREST - NICHOLAS MAROTTA] | B23: 40 | D23: PAID TO IRON CREST, IRON CREST WILL PAY AGENT [IRON CREST - NICHOLAS MAROTTA] | E23: -2300
A24: ASTOUND CHARGEBACK CREDIT (BUFFER) BUFFER REMAINING = 110 [IRON CREST - NICHOLAS MAROTTA] | B24: 335
A27: Meters Details
A29: Personal Meters Details
A30: Customer Name | B30: Service Type | C30: Utility | D30: Client | E30: Date Sold | F30: Status | G30: Usage | H30: Rate | I30: Rejection Reason
A31: KELLY VARGAS | B31: Internet | C31: New York | D31: Astound | E31: 3/21/2026 | F31: Enrolled | G31: 1500 | H31: 400
A32: JAMES QUIER | B32: Internet | C32: Lehigh Valley | D32: Astound | E32: 3/21/2026 | F32: Enrolled | G32: 1000 | H32: 370
A33: BINTA BAH | B33: Internet | C33: New York | D33: Astound | E33: 3/16/2026 | F33: Enrolled | G33: 1000 | H33: 370
A34: JACQUELINE LUNDY | B34: Internet | C34: New York | D34: Astound | E34: 3/19/2026 | F34: Enrolled | G34: 1000 | H34: 370
A35: HILLIARD ODOM | B35: Internet | C35: Lehigh Valley | D35: Astound | E35: 3/21/2026 | F35: Enrolled | G35: 150 | H35: 200
A36: DONALD PATE | B36: Internet | C36: Lehigh Valley | D36: Astound | E36: 3/21/2026 | F36: Enrolled | G36: 150 | H36: 200
A37: CYNTHIA DEAN | B37: Internet | C37: Lehigh Valley | D37: Astound | E37: 3/21/2026 | F37: Enrolled | G37: 150 | H37: 200
A38: VERNA POUGH | B38: Mobile | C38: Lehigh Valley | D38: Astound | E38: 3/16/2026 | F38: Enrolled | G38: 5 | H38: 65
A39: JACQUELINE LUNDY | B39: TV | C39: New York | D39: Astound | E39: 3/19/2026 | F39: Enrolled | G39: 1 | H39: 85
A40: VALERIE CARTY | B40: Internet | C40: New York | D40: Astound | E40: 3/16/2026 | F40: Customer cancel on pre-call | G40: 1000 | H40: 0
A41: ANA PANZO | B41: Internet | C41: New York | D41: Astound | E41: 3/19/2026 | F41: Customer changed mind | G41: 1000 | H41: 0
A42: TIM MCNEIL | B42: Internet | C42: Lehigh Valley | D42: Astound | E42: 3/20/2026 | F42: Credit policy requirements not met | G42: 300 | H42: 0
... A44: TIM MCNEIL | B44: Mobile | C44: Lehigh Valley | D44: Astound | E44: 3/20/2026 | F44: Credit policy requirements not met | G44: 5 | H44: 0
A46: Meter Chargeback Details
A48: Personal Meter Chargeback Details
A49: Customer Name | B49: Service Type | C49: Utility | D49: Client | E49: Date Sold | F49: Status | G49: Usage | H49: Rate | I49: Rejection Reason
A50: JOSEPH ISAAC | B50: Internet | C50: Lehigh Valley | D50: Astound | E50: 2/24/2026 | F50: Chargeback | G50: 300 | H50: -255
A51: JOSEPH ISAAC | B51: TV | C51: Lehigh Valley | D51: Astound | E51: 2/24/2026 | F51: Chargeback | G51: 1 | H51: -80

Sheet 66037-Iron Crest - Nikolas Fisc
A1: Name | C1: Iron Crest - Nikolas Fischer
A2: Production period | C2: 03/16/2026 - 03/22/2026
A3: Payday | C3: 03/27/2026
A4: Repcode | C4: 66037, 770007
A5: Office | C5: Iron Crest Solutions
A6: Team | C6: Iron Crest Solutions
A7: Company | C7: Power Marketing Group, LLC
A9: Summary
A11: Personal Meters | B11: 3,060.00 | D11: Personal Meters Summary
A12: Bonuses | B12: 885 | D12: Status | E12: Sum
A13: Chargeback | B13: -765 | D13: Submitted | E13: 19
A14: Deduction | B14: -3,180.00 | D14: Enrolled | E14: 11
A15: Final pay: | B15: 0 | D15: Rejected | E15: 8
D16: Pending | E16: 0
D17: Accepted rate | E17: 58%
A19: Additions And Deductions
A21: Additions | D21: Deductions
A22: Reason | B22: Amount | D22: Reason | E22: Amount
A23: ASTOUND 3/19 - 3/22 BLITZ - ALFONZO SMITH [IRON CREST - NIKOLAS FISCHER] | B23: 40 | D23: PAID TO IRON CREST, IRON CREST WILL PAY AGENT [IRON CREST - NIKOLAS FISCHER] | E23: -3180
A24: ASTOUND 3/19 - 3/22 BLITZ - EDUARDO QUINONES [IRON CREST - NIKOLAS FISCHER] | B24: 40
A25: ASTOUND 3/19 - 3/22 BLITZ - GREG STATON [IRON CREST - NIKOLAS FISCHER] | B25: 40
A26: ASTOUND CHARGEBACK CREDIT (BUFFER) BUFFER REMAINING = 391.75 [IRON CREST - NIKOLAS FISCHER] | B26: 765
A29: Meters Details
A31: Personal Meters Details
A32: Customer Name | B32: Service Type | C32: Utility | D32: Client | E32: Date Sold | F32: Status | G32: Usage | H32: Rate | I32: Rejection Reason
A33: JOSE MILLAN | B33: Internet | C33: New York | D33: Astound | E33: 3/17/2026 | F33: Enrolled | G33: 1500 | H33: 400
A34: LUIS CHEVEREZ | B34: Internet | C34: New York | D34: Astound | E34: 3/21/2026 | F34: Enrolled | G34: 1500 | H34: 400
A35: ALFONZO SMITH | B35: Internet | C35: Lehigh Valley | D35: Astound | E35: 3/22/2026 | F35: Enrolled | G35: 1500 | H35: 400
A36: ANTHONY GONZALEZ | B36: Internet | C36: New York | D36: Astound | E36: 3/17/2026 | F36: Enrolled | G36: 1000 | H36: 370
A37: GREG STATON | B37: Internet | C37: Lehigh Valley | D37: Astound | E37: 3/21/2026 | F37: Enrolled | G37: 1000 | H37: 370
A38: EDUARDO QUINONES | B38: Internet | C38: Lehigh Valley | D38: Astound | E38: 3/21/2026 | F38: Enrolled | G38: 1000 | H38: 370
A39: DONALD WILLIAMS | B39: Internet | C39: Lehigh Valley | D39: Astound | E39: 3/21/2026 | F39: Enrolled | G39: 150 | H39: 200
A40: DAMIAN CASTRO | B40: Internet | C40: New York | D40: Astound | E40: 3/18/2026 | F40: Enrolled | G40: 150 | H40: 200
A41: NASHAE ALLMOND | B41: Internet | C41: Philadelphia | D41: Astound | E41: 3/21/2026 | F41: Enrolled | G41: 150 | H41: 200
A42: SAM IRBY | B42: Mobile | C42: Lehigh Valley | D42: Astound | E42: 3/20/2026 | F42: Enrolled | G42: 5 | H42: 65
A43: LUIS CHEVEREZ | B43: TV | C43: New York | D43: Astound | E43: 3/21/2026 | F43: Enrolled | G43: 1 | H43: 85
A44: JOHN WALLACE | B44: Internet | C44: Lehigh Valley | D44: Astound | E44: 3/20/2026 | F44: Outbound cancelled | G44: 1500 | H44: 0
... A47: LUIS CHEVEREZ | B47: Mobile | C47: New York | D47: Astound | E47: 3/18/2026 | F47: Customer changed mind | G47: 5 | H47: 0
A49: Meter Chargeback Details
A51: Personal Meter Chargeback Details
A52: Customer Name | B52: Service Type | C52: Utility | D52: Client | E52: Date Sold | F52: Status | G52: Usage | H52: Rate | I52: Rejection Reason
A53: GABRIELLE MARSH | B53: Internet | C53: Lehigh Valley | D53: Astound | E53: 1/5/2026 | F53: Chargeback | G53: 1000 | H53: -350
A54: AMY HATFIELD | B54: Internet | C54: Lehigh Valley | D54: Astound | E54: 3/4/2026 | F54: Chargeback | G54: 300 | H54: -255
A55: GABRIELLE MARSH | B55: TV | C55: Lehigh Valley | D55: Astound | E55: 1/5/2026 | F55: Chargeback | G55: 1 | H55: -80
A56: AMY HATFIELD | B56: TV | C56: Lehigh Valley | D56: Astound | E56: 3/4/2026 | F56: Chargeback | G56: 1 | H56: -80

Sheet 220057-Iron Crest Solutions
A1: Name | C1: Iron Crest Solutions
A2: Production period | C2: 03/16/2026 - 03/22/2026
A3: Payday | C3: 03/27/2026
A4: Repcode | C4: 220057
A5: Office | C5: Iron Crest Solutions
A6: Team | C6: Iron Crest Solutions
A7: Company | C7: Power Marketing Group, LLC
A9: Summary
A11: Bonuses | B11: 10,465.00
A12: Final pay: | B12: 10,465.00
A14: Additions And Deductions
A16: Additions
A17: Reason | B17: Amount
A18: FUNDING TO PAY IRON CREST AGENTS DIRECTLY [IRON CREST] | B18: 10465

Sheet Master Report
A1: Sales list
A2: Repcode | B2: Account Number | C2: Customer Name | D2: Utility | E2: Service Type | F2: Date Sold | G2: Status | H2: Client | I2: State | J2: Usage
A3: 66038 | B3: 18496002 | C3: JACQUELINE LUNDY | D3: New York | E3: Internet | F3: 3/19/2026 | G3: Accepted | H3: Astound | I3: N/A | J3: 1000
A4: 66038 | B4: 18496002 | C4: JACQUELINE LUNDY | D4: New York | E4: TV | F4: 3/19/2026 | G4: Accepted | H4: Astound | I4: N/A | J4: 1
A5: 66037 | B5: 9215306 | C5: LUIS CHEVEREZ | D5: New York | E5: Internet | F5: 3/21/2026 | G5: Accepted | H5: Astound | I5: N/A | J5: 1500
A6: 66037 | B6: 9215306 | C6: LUIS CHEVEREZ | D6: New York | E6: TV | F6: 3/21/2026 | G6: Accepted | H6: Astound | I6: N/A | J6: 1
A7: 66048 | B7: 49034901 | C7: WOODROW W DUNN | D7: New York | E7: Internet | F7: 3/18/2026 | G7: Accepted | H7: Astound | I7: N/A | J7: 1000
A8: 66048 | B8: 49034901 | C8: WOODROW W DUNN | D8: New York | E8: TV | F8: 3/18/2026 | G8: Accepted | H8: Astound | I8: N/A | J8: 1
A9: 66037 | B9: 68027805 | C9: ALFONZO SMITH | D9: Lehigh Valley | E9: Internet | F9: 3/22/2026 | G9: Accepted | H9: Astound | I9: N/A | J9: 1500
A10: 66075 | B10: 61680508 | C10: GEORGE CABRERA | D10: Lehigh Valley | E10: Internet | F10: 3/18/2026 | G10: Accepted | H10: Astound | I10: N/A | J10: 1500
A11: 66037 | B11: 2293806 | C11: JOSE MILLAN | D11: New York | E11: Internet | F11: 3/17/2026 | G11: Accepted | H11: Astound | I11: N/A | J11: 1500
A12: 66038 | B12: 5441203 | C12: KELLY VARGAS | D12: New York | E12: Internet | F12: 3/21/2026 | G12: Accepted | H12: Astound | I12: N/A | J12: 1500
A13: 66037 | B13: 15662602 | C13: ANTHONY GONZALEZ | D13: New York | E13: Internet | F13: 3/17/2026 | G13: Accepted | H13: Astound | I13: N/A | J13: 1000
A14: 66038 | B14: 48991501 | C14: BINTA BAH | D14: New York | E14: Internet | F14: 3/16/2026 | G14: Accepted | H14: Astound | I14: N/A | J14: 1000
... A71: 66038 | B71: 65920414 | C71: TIM MCNEIL | D71: Lehigh Valley | E71: Mobile | F71: 3/20/2026 | G71: Credit policy requirements not met | H71: Astound | I71: N/A | J71: 5

Sheet l

Sheet Commission Rules
A1: IRON CREST SOLUTIONS — COMMISSION RULES & REFERENCE
A2: Last Updated: 3/25/2026 | Created from initial setup conversation with Claude
A4: SECTION 1: COMPANY STRUCTURE
A5: Company: | B5: Iron Crest Solutions (under Power Marketing Group, LLC)
A6: Primary Provider: | B6: Astound (active)
A7: Former Provider: | B7: Optimum (no longer active after 3/27/2026 payroll)
A8: PMG Account Code: | B8: 220057 (Iron Crest Solutions)
A10: SECTION 2: ORG STRUCTURE & ROLES
A11: Person | B11: Role & Notes
A12: Nikolas (Nik) Fischer | B12: Owner/Rep. Gets Col H (full Iron Crest Executive Pay) on personal sales. Pools with Nick, splits 50/50. NO reserve.
A13: Nicholas (Nick) Marotta | B13: Owner/Rep. Gets Col H (full Iron Crest Executive Pay) on personal sales. Pools with Nik, splits 50/50. NO reserve.
A14: Jose Luis Molina | B14: Leader. Col C rate. Reports to Dan. Individual comp — Jose Team dissolved effective 4/2026 payroll. 15% reserve.
A15: Cindy Reyes | B15: Leader. Col C rate. Reports to Dan. Individual comp — no longer pooled with Jose (effective 4/2026). 15% reserve.
A16: Maria Rico | B16: Leader. Col C rate. Reports to Dan. Individual comp — no longer pooled with Jose (effective 4/2026). 15% reserve.
A17: Samuel (Sam) Chapman | B17: Leader. Col C rate. No manager above him — no manager override on his sales. 15% reserve.
A18: Daniel (Dan) DeLeon | B18: Manager. Col D rate on personal sales. $10 override on team sales (Jose/Cindy/Maria). 15% reserve.
A19: Andrew Unglert | B19: New rep. Elevated Personal Sales rate (Col J). Transitions to standard manager comp once he builds a qualifying team. 15% reserve.
A20: Stefano Fischer | B20: Operations. Fixed override (Comp Plan Col F) on OTHER people's sales. Override on ALL sales including owner sales. NO $10 override on his own personal sales or his reps' sales (in perpetuity). Personal sales paid at Col J (Elevated). See Section 8.
A21: Joei Ruffino | B21: Accounting. Fixed override (Comp Plan Col G). Override on ALL sales including owner sales.
A22: Sean (SMF) | B22: Director of Sales. Fixed override on 300 Mbps+ only (Col E). Does NOT get override on owner sales.
A23: ⚠ Dan & SMF do NOT get overrides on owner (Nik/Nick) sales.
A24: ⚠ Stefano & Joei DO get overrides on owner sales — paid from Iron Crest profit (Row 20), NOT owner commissions.
A25: ⚠ Manager bonus: $15/order (instead of $10) when team hits 100+ connects/week.
A27: SECTION 3: COMMISSION CALCULATION RULES
A28: Commissions Paid On: | B28: Installed/Accepted orders only (Status = 'Accepted' or 'Enrolled' on Master Report)
A29: Chargeback Window: | B29: Customer must stay active 90 days post-install. If cancelled within 90 days, full chargeback.
A30: SPEED TIER MAPPING:
A31: Usage 1500 = 1 Gig+ | B31: Usage 1000 = 1 Gig
A32: Usage 600 = 600 Mbps | B32: Usage 300 = 300 Mbps
A33: Usage 150 = 150 Mbps | B33: Usage 5 = Unlimited Mobile
A34: Usage 1 = TV
A35: RATES BY ROLE:
A36: Owners (Nik & Nick): | B36: Col H (Iron Crest Executive Pay) — full all-in rate. Pool sales, split 50/50.
A37: Leaders (Jose, Cindy, Maria, Sam): | B37: Col C (Leader rate) from Comp Plan.
A38: Managers (Dan, future mgrs): | B38: Col D (Manager rate) on personal sales.
A39: Reps (future hires): | B39: Col B (Rep rate) from Comp Plan.
A41: SECTION 4: RESERVE POLICY
A42: Reserve Rate: | B42: 15% of gross commission (calculated on gross BEFORE chargebacks)
A43: Reserve Cap: | B43: $2,500 — stop deducting once YTD reserve reaches $2,500
A44: Exempt from Reserve: | B44: Owners (Nik Fischer & Nick Marotta) — NO reserve
A45: Reserve applies to: | B45: All leaders, managers, and reps
A46: Chargeback from reserve: | B46: Rep's original commission deducted from YTD reserve. Iron Crest profit portion absorbed by Iron Crest (deducted from Col M).
A47: NET COMP formula: | B47: Gross commission (before chargebacks) minus 15% reserve = NET COMP. Chargebacks hit YTD reserve, NOT current paycheck.
A48: YTD Reserve formula: | B48: Prior YTD Reserve - Chargebacks (rep portion) + New 15% Reserve = New YTD Reserve
A50: SECTION 5: OVERRIDE RULES
A51: Override Chain (per installed order):
A52: 1. Seller gets paid (Rep/Leader/Manager rate based on role)
A53: 2. If seller has a Manager → Manager gets $10 override ($15 at 100+ connects/week)
A54: 3. SMF (Sean) gets Col E override on 300 Mbps+ orders (NOT on owner sales)
A55: 4. Stefano gets Col F override on 150 Mbps+ orders (ALL sales including owners)
A56: 5. Joei gets Col G override on 150 Mbps+ orders (ALL sales including owners)
A57: 6. Iron Crest Overrides (Col M) = remaining profit per sale
A58: Owner sales override treatment: | B58: Stefano & Joei overrides on owner sales shown on Row 20 (Operations Override), deducted from Iron Crest Net Overrides.
A60: SECTION 6: PMG RECONCILIATION
A61: PMG Payout formula: | B61: B19 (Gross Commissions) + H19 (Blitz Bonuses) + M22 (Total Overrides Paid) = PMG Payout
A62: Blitz Bonuses (Col H): | B62: I19 (Stefano) + J19 (Joei) + K19 (SMF) + L19 (Dan) + M19 (Iron Crest Overrides)
A63: Total Overrides Paid (M22): | B63: {=I20 (Stefano) + J20 (Joei) + K20 (SMF) + L20 (Dan) + M20 (Iron Crest Overrides)} -> #NAME?
A64: Direct Deposit Fee: | B64: $2.50 per rep receiving payout. Not applied to owners or zero-pay reps.
A66: SECTION 7: WEEKLY WORKFLOW
A67: 1. Open this workbook
A68: 2. Open new PMG file in separate Excel window
A69: 3. Copy new Master Report + rep tabs into this workbook (rename Master Report with date)
A70: 4. Open Claude add-in: 'New week — build payout sheet for WE [date]'
A71: 5. Claude reads Master Report, applies Comp Plan rates, creates new payout tab
A72: 6. Claude creates individual Rep Commission Statement sub-tabs (filtered orders, commissions, chargebacks per rep)
A73: 7. Review and confirm numbers before processing payroll
A74: 8. Save workbook — all weeks stay as historical record
A75: SECTION 8: AMENDED SPECIAL COMP PLAN — PERSONAL SALES
A76: Effective Date: | B76: TBD — temporary elevated plan, duration unknown
A77: Representatives: | B77: Stefano Fischer, Andrew Unglert, Sean (SMF)
A78: Rate Column: | B78: Col J (Elevated Personal Sales) on Comp Plan tab. All three share the same rates.
A79: Transition: | B79: Each rep transitions to standard manager comp (Col D) once they build and develop a team that qualifies them for overrides.
A81: STEFANO — SPECIAL RULES
A82: Personal Sales Rate: | B82: Col J (Elevated Personal Sales). No $10 operations override on his own personal sales.
A83: Operations Override (Col F): | B83: Still receives $10 Col F override on OTHER people's sales (all sales including owners) — unchanged.
A84: No Override on Own Reps: | B84: Stefano does NOT receive $10 operations override on sales from reps under him — in perpetuity.
A85: Sean's Override on Stefano: | B85: Sean's Col E override on Stefano's sales reduced to $15 (where applicable) until Stefano qualifies for manager comp, then Sean resumes normal Col E overrides.
A87: ANDREW UNGLERT — SPECIAL RULES
A88: Personal Sales Rate: | B88: Col J (Elevated Personal Sales).
A89: Sean's Override on Andrew: | B89: Sean's Col E override on Andrew's sales reduced to $15 (where applicable) until Andrew qualifies for manager comp, then Sean resumes normal Col E overrides.
A91: SEAN (SMF) — PERSONAL SALES RULES
A92: Personal Sales Rate: | B92: Col J (Elevated Personal Sales). Sean uses these rates ONLY when he personally sells.
A93: Overrides on Sean's Sales: | B93: NO overrides paid on Sean's personal sales EXCEPT: Joei (Col G) and Iron Crest (Col I). Stefano does NOT receive Col F override on Sean's personal sales.
A94: Sean's Col E Override: | B94: Sean does NOT receive a Col E override on his own personal sales. Col E still applies on all other reps' sales as normal.
A95: Dan Override: | B95: Dan does NOT receive manager override on Sean's personal sales.
A97: ⚠ SUMMARY — OVERRIDE EXCEPTIONS FOR THIS PLAN
A98: ⚠ Stefano's personal sales: No $10 self-override. Sean's override reduced to $15. All other overrides normal.
A99: ⚠ Andrew's personal sales: Sean's override reduced to $15. All other overrides normal.
A100: ⚠ Sean's personal sales: Only Joei (Col G) and Iron Crest (Col I) receive overrides. No Stefano (Col F), no Col E, no Dan override.
A101: ⚠ Stefano does NOT earn $10 override on his own reps' sales — in perpetuity (even after transition).

Sheet 4.10.26
A2: Commissions 4/10/26
A3: PMG PAYOUT | B3: 12230
A4: Spreadsheet confirmation | B4: =SUM(B20+H20+M23) -> 12230
A5: Totals: Column B/H/N | B5: =SUM(B20+H20+M23) -> 12230
A7: Iron Crest Employee | B7: Gross Commissions | C7: Connects | D7: Deductions | E7: Commission After Deductions | F7: Reserve-15% | G7: YTD Reserve Balance | H7: NET BONUS | I7: Stefano Override | J7: Joei Override | K7: Sean Override | L7: Dan Override | M7: Iron Crest Overrides | N7: NET COMP | O7: Direct Deposit Fee | P7: PAYROLL TOTAL | Q7: Comments
A8: Nik Fischer | B8: 4440 | C8: 14 | E8: 0 | N8: =B8 -> 4440 | O8: 0 | P8: =N8-O8 -> 4440 | Q8: Owners NOT pooling. Shanelle Tucker & Ivette Velezquez reassigned to Sean.
A9: Nick Marotta | B9: 1140 | C9: 4 | E9: 0 | N9: =B9 -> 1140 | O9: 0 | P9: =N9-O9 -> 1140
A10: Sam Chapman | B10: 2555 | C10: 15 | D10: 0 | E10: 2555 | F10: =B10*15% -> 383.25 | G10: 1473.5 | I10: 110 | J10: 55 | K10: 340 | L10: 0 | M10: 1390 | N10: =B10-F10 -> 2171.75 | O10: 2.5 | P10: =N10-O10 -> 2169.25
A11: Jose Molina | B11: 705 | C11: 3 | D11: 300 | E11: 705 | F11: 0 | G11: 3217.5 | I11: 40 | J11: 20 | K11: 105 | L11: 30 | M11: 440 | N11: =B11-F11 -> 705 | O11: 2.5 | P11: =N11-O11 -> 702.5 | Q11: Jose 3 connects. Maria chargeback $300 from reserve (team).
A12: Cindy Reyes | B12: 0 | F12: 0 | G12: 0 | N12: =B12-F12 -> 0 | P12: =N12-O12 -> 0
A13: Monica Rico | B13: 0 | F13: 0 | G13: 0 | N13: =B13-F13 -> 0 | P13: =N13-O13 -> 0
A14: Nicholas Digiamo | B14: 0 | F14: =B14*15% -> 0 | G14: 77.25 | N14: =B14-F14 -> 0 | P14: 0
A15: Jeffrey Scott | B15: 0 | F15: =B15*15% -> 0 | G15: 33.75 | N15: =B15-F15 -> 0 | P15: 0
A16: Stefano Fischer | B16: 0 | P16: =I20+I21 -> 310
A17: Joei Ruffino | B17: 0 | P17: =J20+J21 -> 165
A18: Dan DeLeon | B18: 60 | C18: 1 | E18: 60 | F18: =B18*15% -> 9 | G18: 63.75 | I18: 0 | J18: 0 | K18: 0 | L18: 0 | M18: 0 | N18: =B18-F18 -> 51 | O18: 2.5 | P18: =N18-O18+L20 -> 78.5 | Q18: $30 override from Jose's 3 team orders ($10 × 3)
A19: Sean M. Fischer | B19: 660 | C19: 2 | E19: 660 | F19: =B19*15% -> 99 | G19: 99 | I19: 0 | J19: 10 | K19: 0 | L19: 0 | M19: 130 | N19: =B19-F19 -> 561 | O19: 2.5 | P19: =N19-O19+K20 -> 1003.5 | Q19: Sean personal: Shanelle Tucker & Ivette Velezquez (1G+ each). Col J rate + override on others.
A20: TOTAL | B20: =SUM(B8:B19) -> 9560 | C20: =SUM(C8:C19) -> 39 | D20: =SUM(D8:D19) -> 300 | E20: =SUM(E8:E19) -> 3980 | F20: =SUM(F8:F19) -> 491.25 | G20: =SUM(G8:G19) -> 4964.75 | H20: =SUM(H8:H19) -> 0 | I20: =SUM(I8:I19) -> 150 | ... P20: =SUM(P8:P19) -> 10008.75
A21: Operations Override (Joei/Stefano) | I21: 160 | J21: 80 | M21: =SUM(I21+J21) -> 240
A22: Iron Crest Net Overrides | M22: =M20-M21 -> 1720
A23: Total Overrides Paid | M23: =I20+J20+K20+L20+M20 -> 2670
A25: IRON CREST ORDERS
A26: Cust Name | B26: Service | C26: Rep | D26: Provider | E26: Amount
A27: DAMIAN ARROYO | B27: Internet | C27: Dan DeLeon | D27: 150 Mbps | E27: 60
A28: CRISTAL MARMOL | B28: Internet | C28: Jose Molina | D28: 1 Gig+ | E28: 235
A29: GLADYS MARTINEZ | B29: Internet | C29: Jose Molina | D29: 1 Gig+ | E29: 235
A30: RAMON E PICHARDO | B30: Internet | C30: Jose Molina | D30: 1 Gig+ | E30: 235
A31: CHRISTINE STERNER | B31: Internet | C31: Nick Marotta | D31: 150 Mbps | E31: 200
A32: MAMADU JALLOH | B32: Internet | C32: Nick Marotta | D32: 1 Gig | E32: 370
A33: MONIQUE WHEELER | B33: Internet | C33: Nick Marotta | D33: 150 Mbps | E33: 200
A34: ROBERT WOODARD | B34: Internet | C34: Nick Marotta | D34: 1 Gig | E34: 370
A35: ARCADIO DEJESUS | B35: Internet | C35: Nik Fischer | D35: 1 Gig | E35: 370
A36: DEANGELO WILLIAMS | B36: Internet | C36: Nik Fischer | D36: 1 Gig+ | E36: 400
A37: ERIC BELFORT | B37: Internet | C37: Nik Fischer | D37: 1 Gig+ | E37: 400
A38: EVY BOURGEIOS | B38: Internet | C38: Nik Fischer | D38: 1 Gig | E38: 370
... A65: THERESA KUGELMAN | B65: Internet | C65: Sam Chapman | D65: 1 Gig | E65: 210
A67: CHARGEBACKS
A68: Cust Name | B68: Service | C68: Rep | D68: Speed | E68: Amount
A69: VICTOR SKARBNIK | B69: Internet | C69: Maria Rico | D69: 1 Gig+ | E69: -300

Sheet Owner Report - 4.5.26
A1: IRON CREST SOLUTIONS
A2: Weekly Payout Report — WE 4/5/2026
A3: Production Period: 03/30/2026 – 04/05/2026 | Payday: 04/10/2026
A5: WEEKLY P&L SNAPSHOT
A6: PMG Agent Funding | B6: 12230
A7: March Optimum/Astound Incentive (174 × $15) | B7: 2610
A8: March Astound PA/MD/DC Incentive (73 × $40) | B8: 2920
A9: Less: PMG Onboarding Deduction | B9: -253.5
A10: TOTAL PMG FUNDING RECEIVED | B10: =SUM(B6:B9) -> 17506.5
A11: Less: Rep/Leader Commissions | B11: ='4.10.26'!B20 -> 9560
A12: Less: Stefano Override | B12: ='4.10.26'!I20+'4.10.26'!I21 -> 310
A13: Less: Joei Override | B13: ='4.10.26'!J20+'4.10.26'!J21 -> 165
A14: Less: SMF (Sean) Override | B14: ='4.10.26'!K20 -> 445
A15: Less: Dan Override | B15: ='4.10.26'!L20 -> 30
A16: Less: Direct Deposit Fees | B16: ='4.10.26'!O20 -> 10
A17: Less: Chargeback Loss (IC portion) | B17: 0 | C17: Buffer covered at PMG. $300 from Jose reserve → IC.
A18: IRON CREST NET PROFIT | B18: =B10-B11-B12-B13-B14-B15-B16-B17 -> 6986.5
A20: OWNER COMPENSATION
A21: Nik Fischer Personal Sales | B21: 14 orders | C21: ='4.10.26'!B8 -> 4440 | D21: ROSALINDA MORALES (1G+/Mob), DEANGELO WILLIAMS (1G+), ERIC BELFORT (1G+), JOCEY VAGA (1G+), TAMEYA TAYLOR (1G), ARCADIO DEJESUS (1G), EVY BOURGEIOS (1G), JESS RODRIGUEZ (1G), MALIK JOHNSON (1G), NAYSHA CLARKE (1G), LEONARD WHITMORE (300/TV), MARIA GONZALEZ (150)
A22: Nick Marotta Personal Sales | B22: 4 orders | C22: ='4.10.26'!B9 -> 1140 | D22: MAMADU JALLOH (1G), ROBERT WOODARD (1G), CHRISTINE STERNER (150), MONIQUE WHEELER (150)
A23: Owner Pool / Split | C23: N/A — Paid individually this week
A24: Iron Crest Net Profit (above) | C24: =B18 -> 6986.5
A25: Chargeback Recovery (Jose Reserve) | C25: 300
A26: TOTAL OWNER INCOME | C26: =C21+C22+C24+C25 -> 12866.5
A28: PAYROLL BREAKDOWN
A29: Employee | B29: Gross Comm. | C29: Connects | D29: Reserve (15%) | E29: YTD Reserve | F29: NET COMP | G29: Override | H29: DD Fee | I29: PAYROLL
A30: Nik Fischer | B30: ='4.10.26'!B8 -> 4440 | C30: ='4.10.26'!C8 -> 14 | D30: N/A | E30: N/A | F30: ='4.10.26'!N8 -> 4440 | H30: ='4.10.26'!O8 -> 0 | I30: ='4.10.26'!P8 -> 4440
A31: Nick Marotta | B31: ='4.10.26'!B9 -> 1140 | C31: ='4.10.26'!C9 -> 4 | D31: N/A | E31: N/A | F31: ='4.10.26'!N9 -> 1140 | H31: ='4.10.26'!O9 -> 0 | I31: ='4.10.26'!P9 -> 1140
A32: Sam Chapman | B32: ='4.10.26'!B10 -> 2555 | C32: ='4.10.26'!C10 -> 15 | D32: ='4.10.26'!F10 -> 383.25 | E32: ='4.10.26'!G10 -> 1473.5 | F32: ='4.10.26'!N10 -> 2171.75 | H32: ='4.10.26'!O10 -> 2.5 | I32: ='4.10.26'!P10 -> 2169.25
A33: Jose Molina (team) | B33: ='4.10.26'!B11 -> 705 | C33: ='4.10.26'!C11 -> 3 | D33: ='4.10.26'!F11 -> 0 | E33: ='4.10.26'!G11 -> 3217.5 | F33: ='4.10.26'!N11 -> 705 | H33: ='4.10.26'!O11 -> 2.5 | I33: ='4.10.26'!P11 -> 702.5
A34: Dan DeLeon | B34: ='4.10.26'!B18 -> 60 | C34: ='4.10.26'!C18 -> 1 | D34: ='4.10.26'!F18 -> 9 | E34: ='4.10.26'!G18 -> 63.75 | F34: ='4.10.26'!N18 -> 51 | G34: ='4.10.26'!L20 -> 30 | H34: ='4.10.26'!O18 -> 2.5 | I34: ='4.10.26'!P18 -> 78.5
A35: Stefano Fischer | G35: ='4.10.26'!P16 -> 310 | I35: ='4.10.26'!P16 -> 310
A36: Joei Ruffino | G36: ='4.10.26'!P17 -> 165 | I36: ='4.10.26'!P17 -> 165
A37: Sean M. Fischer | B37: ='4.10.26'!B19 -> 660 | C37: ='4.10.26'!C19 -> 2 | D37: ='4.10.26'!F19 -> 99 | E37: ='4.10.26'!G19 -> 99 | F37: ='4.10.26'!N19 -> 561 | G37: ='4.10.26'!K20 -> 445 | H37: ='4.10.26'!O19 -> 2.5 | I37: ='4.10.26'!P19 -> 1003.5
A38: TOTAL PAYROLL | I38: =SUM(I30:I37) -> 10008.75
A40: OVERRIDE DETAIL
A41: Override Recipient | B41: Sam's Orders | C41: Jose Team Orders | D41: Sean's Orders | E41: Owner Orders (Nik/Nick) | F41: TOTAL
A42: Stefano Fischer | B42: 110 | C42: 40 | D42: 0 | E42: 160 | F42: =SUM(B42:E42) -> 310
A43: Joei Ruffino | B43: 55 | C43: 20 | D43: 10 | E43: 80 | F43: =SUM(B43:E43) -> 165
A44: SMF (Sean) | B44: 340 | C44: 105 | D44: 0 | E44: 0 | F44: =SUM(B44:E44) -> 445
A45: Dan DeLeon | B45: 0 | C45: 30 | D45: 0 | E45: 0 | F45: =SUM(B45:E45) -> 30
A46: Iron Crest Profit | B46: 1390 | C46: 440 | D46: 130 | E46: 0 | F46: =SUM(B46:E46) -> 1960
A47: TOTAL PER GROUP | B47: =SUM(B42:B46) -> 1895 | C47: =SUM(C42:C46) -> 635 | D47: =SUM(D42:D46) -> 140 | E47: =SUM(E42:E46) -> 240 | F47: =SUM(F42:F46) -> 2910
A49: ALL ACCEPTED ORDERS (39)
A50: Customer | B50: Service | C50: Tier | D50: Sold By | E50: Exec Rate | F50: IC Profit | G50: Rep Comm
A51: ANDREW WILLIAMS | B51: Internet | C51: 1 Gig | D51: Sam Chapman | E51: 370 | F51: 115 | G51: 210
A52: DARLINE LOCKETT | B52: Internet | C52: 1 Gig | D52: Sam Chapman | E52: 370 | F52: 115 | G52: 210
A53: DIANA M GUTMAN | B53: Internet | C53: 1 Gig+ | D53: Sam Chapman | E53: 400 | F53: 115 | G53: 235
A54: EDWARD FLOYD | B54: Mobile | C54: Unlm. Mobile | D54: Sam Chapman | E54: 65 | F54: 20 | G54: 45
A55: GLADYS LABOR | B55: Internet | C55: 1 Gig | D55: Sam Chapman | E55: 370 | F55: 115 | G55: 210
A56: GLADYS LABOR | B56: TV | C56: TV | D56: Sam Chapman | E56: 85 | F56: 35 | G56: 50
A57: IRVIN SWEET | B57: Internet | C57: 1 Gig | D57: Sam Chapman | E57: 370 | F57: 115 | G57: 210
A58: IRVIN SWEET | B58: TV | C58: TV | D58: Sam Chapman | E58: 85 | F58: 35 | G58: 50
A59: JANE M CHARLES | B59: Internet | C59: 1 Gig+ | D59: Sam Chapman | E59: 400 | F59: 115 | G59: 235
A60: JEROME HANEY | B60: Internet | C60: 1 Gig | D60: Sam Chapman | E60: 370 | F60: 115 | G60: 210
A61: JOANN PALESTRINI | B61: Internet | C61: 1 Gig | D61: Sam Chapman | E61: 370 | F61: 115 | G61: 210
A62: RAPHAEL MARSH | B62: Internet | C62: 1 Gig | D62: Sam Chapman | E62: 370 | F62: 115 | G62: 210
... A89: ROBERT WOODARD | B89: Internet | C89: 1 Gig | D89: Nick Marotta | E89: 370 | F89: 0 | G89: 370
A90: TOTALS | B90: 39 orders | E90: =SUM(E51:E89) -> 12230 | F90: =SUM(F51:F89) -> 1960 | G90: =SUM(G51:G89) -> 9560
A92: CHARGEBACKS
A93: Customer | B93: Original Rep | C93: Provider | D93: Tier | E93: PMG Chargeback | F93: Rep Reserve Hit | G93: IC Net Loss
A94: Victor Skarbnik | B94: Maria Rico (→ Jose reserve) | C94: Optimum | D94: 1 Gig+ | E94: -390 | F94: -300 | G94: 0
A95: TOTAL CHARGEBACK IMPACT | E95: =SUM(E94:E94) -> -390 | F95: =SUM(F94:F94) -> -300 | G95: =SUM(G94:G94) -> 0

Sheet Rep - Sam Chapman 4.5
A1: IRON CREST SOLUTIONS
A2: Commission Statement — Sam Chapman
A3: Week Ending: 4/5/2026 | Payday: 04/10/2026
A5: YOUR ACCEPTED ORDERS
A6: Customer | B6: Service | C6: Tier | D6: Your Commission
A7: ANDREW WILLIAMS | B7: Internet | C7: 1 Gig | D7: 210
A8: DARLINE LOCKETT | B8: Internet | C8: 1 Gig | D8: 210
A9: DIANA M GUTMAN | B9: Internet | C9: 1 Gig+ | D9: 235
A10: EDWARD FLOYD | B10: Mobile | C10: Unlm. Mobile | D10: 45
A11: GLADYS LABOR | B11: Internet | C11: 1 Gig | D11: 210
A12: GLADYS LABOR | B12: TV | C12: TV | D12: 50
A13: IRVIN SWEET | B13: Internet | C13: 1 Gig | D13: 210
A14: IRVIN SWEET | B14: TV | C14: TV | D14: 50
A15: JANE M CHARLES | B15: Internet | C15: 1 Gig+ | D15: 235
A16: JEROME HANEY | B16: Internet | C16: 1 Gig | D16: 210
A17: JOANN PALESTRINI | B17: Internet | C17: 1 Gig | D17: 210
A18: RAPHAEL MARSH | B18: Internet | C18: 1 Gig | D18: 210
... A21: THERESA KUGELMAN | B21: Internet | C21: 1 Gig | D21: 210
A22: TOTAL | B22: 15 orders | D22: =SUM(D7:D21) -> 2555
A24: COMPENSATION SUMMARY
A25: Gross Commission | B25: =D22 -> 2555
A26: Less: Reserve (15%) | B26: =-B25*0.15 -> -383.25
A27: Less: DD Fee | B27: -2.5
A28: NET COMP | B28: =B25+B26+B27 -> 2169.25
A29: YTD Reserve Balance | B29: 1473.5
A31: No chargebacks this period.

Sheet Rep - Jose Team 4.5
A1: IRON CREST SOLUTIONS
A2: Commission Statement — Jose Molina (Team)
A3: Week Ending: 4/5/2026 | Payday: 04/10/2026
A4: Includes: Jose, Cindy Reyes, Maria Rico (treated as one unit)
A6: YOUR ACCEPTED ORDERS
A7: Customer | B7: Sold By | C7: Tier | D7: Commission
A8: CRISTAL MARMOL | B8: Jose | C8: 1 Gig+ | D8: 235
A9: GLADYS MARTINEZ | B9: Jose | C9: 1 Gig+ | D9: 235
A10: RAMON E PICHARDO | B10: Jose | C10: 1 Gig+ | D10: 235
A11: TOTAL | B11: 3 orders | D11: =SUM(D8:D10) -> 705
A13: CHARGEBACKS
A14: Customer | B14: Original Seller | C14: Tier | D14: Reserve Hit
A15: Victor Skarbnik | B15: Maria Rico | C15: 1 Gig+ | D15: -300
A17: COMPENSATION SUMMARY
A18: Gross Commission | B18: =D11 -> 705
A19: Less: Reserve (15%) | B19: 0
A20: Chargeback (from reserve) | B20: -300
A21: Less: DD Fee | B21: -2.5
A22: NET COMP | B22: =B18+B19+B21 -> 702.5
A23: YTD Reserve Balance | B23: 2917.5

Sheet Rep - Dan DeLeon 4.5
A1: IRON CREST SOLUTIONS
A2: Commission Statement — Dan DeLeon
A3: Week Ending: 4/5/2026 | Payday: 04/10/2026
A5: YOUR ACCEPTED ORDERS
A6: Customer | B6: Service | C6: Tier | D6: Your Commission
A7: DAMIAN ARROYO | B7: Internet | C7: 150 Mbps | D7: 60
A8: TOTAL | B8: 1 order | D8: =SUM(D7:D7) -> 60
A10: COMPENSATION SUMMARY
A11: Gross Commission | B11: =D8 -> 60
A12: Less: Reserve (15%) | B12: =-B11*0.15 -> -9
A13: Override (Jose Team) | B13: 30
A14: Less: DD Fee | B14: -2.5
A15: NET COMP | B15: =B11+B12+B13+B14 -> 78.5
A16: YTD Reserve Balance | B16: 63.75
A18: No chargebacks this period.

Sheet Rep - Sean Fischer 4.5
A1: IRON CREST SOLUTIONS
A2: Commission Statement — Sean M. Fischer
A3: Week Ending: 4/5/2026 | Payday: 04/10/2026
A5: YOUR ACCEPTED ORDERS
A6: Customer | B6: Service | C6: Tier | D6: Your Commission
A7: IVETTE VELEZQUEZ | B7: Internet | C7: 1 Gig+ | D7: 330
A8: SHANELLE TUCKER | B8: Internet | C8: 1 Gig+ | D8: 330
A9: TOTAL | B9: 2 orders | D9: =SUM(D7:D8) -> 660
A11: COMPENSATION SUMMARY
A12: Gross Commission | B12: =D9 -> 660
A13: Less: Reserve (15%) | B13: =-B12*0.15 -> -99
A14: Override (SMF Director) | B14: 445
A15: Less: DD Fee | B15: -2.5
A16: NET COMP | B16: =B12+B13+B14+B15 -> 1003.5
A17: YTD Reserve Balance | B17: 99
A19: No chargebacks this period.
